[
  {
    "author": "FelixAndersen",
    "link_thumb": "https://live.staticflickr.com/65535/51695084449_0ce8f6b768_o.gif",
    "link_bin": "https://github.com/lmbstudiocontact/mb5_3/raw/main/809.bin",
    "id_bin": "809",
    "list_language": [],
    "array_tags": [
      "digital",
      "date",
      "distance",
      "weather",
      "calories",
      "battery",
      "steps"
    ],
    "list_album": [
      {
        "id_album": "2433880",
        "link_thumb": "https://live.staticflickr.com/65535/51695084449_0ce8f6b768_o.gif",
        "title": "None"
      }
    ]
  },
  {
    "author": "None",
    "link_thumb": "https://live.staticflickr.com/65535/51700056226_61ee9c6bd6_o.gif",
    "link_bin": "https://github.com/lmbstudiocontact/mb5_38/raw/main/M0045.bin",
    "id_bin": "M0045",
    "list_language": [],
    "array_tags": [],
    "list_album": [
      {
        "id_album": "-583089738",
        "link_thumb": "https://live.staticflickr.com/65535/51700056226_61ee9c6bd6_o.gif",
        "title": "Mifit Store"
      }
    ]
  },
  {
    "author": "nekofirefox_AR",
    "link_thumb": "https://live.staticflickr.com/65535/51694247748_7ff4b9e05e_o.gif",
    "link_bin": "https://github.com/lmbstudiocontact/mb5_12/raw/main/1038.bin",
    "id_bin": "1038",
    "list_language": [],
    "array_tags": [
      "digital",
      "heartrate"
    ],
    "list_album": [
      {
        "id_album": "2433880",
        "link_thumb": "https://live.staticflickr.com/65535/51694247748_7ff4b9e05e_o.gif",
        "title": "None"
      }
    ]
  },
  {
    "author": "Dailson f.c",
    "link_thumb": "https://live.staticflickr.com/65535/51694681284_eb790b22e3_o.gif",
    "link_bin": "https://github.com/lmbstudiocontact/mb5_12/raw/main/1269.bin",
    "id_bin": "1269",
    "list_language": [],
    "array_tags": [
      "digital",
      "date",
      "distance",
      "heartrate",
      "weather",
      "calories",
      "battery",
      "steps"
    ],
    "list_album": [
      {
        "id_album": "2433880",
        "link_thumb": "https://live.staticflickr.com/65535/51694681284_eb790b22e3_o.gif",
        "title": "None"
      }
    ]
  },
  {
    "author": "LMB Studio",
    "link_thumb": "https://live.staticflickr.com/65535/51695781824_9087e34b43_o.gif",
    "link_bin": "https://github.com/lmbstudiocontact/mb5_3/raw/main/Boy_L6_-944583170.bin",
    "id_bin": "Boy_L6_-944583170",
    "list_language": [
      {
        "author": "LMB Studio",
        "link_thumb": "https://live.staticflickr.com/65535/51695377943_b9f1bfd91d_o.gif",
        "link_bin": "https://github.com/lmbstudiocontact/mb5_3/raw/main/Boy_L6_-944583170_English.bin",
        "name_language": "English",
        "id_bin_language": "Boy_L6_-944583170_English"
      },
      {
        "author": "LMB Studio",
        "link_thumb": "https://live.staticflickr.com/65535/51695102161_492a2d59ff_o.gif",
        "link_bin": "https://github.com/lmbstudiocontact/mb5_3/raw/main/Boy_L6_-944583170_Portuguese.bin",
        "name_language": "Portuguese",
        "id_bin_language": "Boy_L6_-944583170_Portuguese"
      },
      {
        "author": "LMB Studio",
        "link_thumb": "https://live.staticflickr.com/65535/51694310847_8d91cc39ec_o.gif",
        "link_bin": "https://github.com/lmbstudiocontact/mb5_3/raw/main/Boy_L6_-944583170_Russian.bin",
        "name_language": "Russian",
        "id_bin_language": "Boy_L6_-944583170_Russian"
      },
      {
        "author": "LMB Studio",
        "link_thumb": "https://live.staticflickr.com/65535/51694311277_b32c0a1822_o.gif",
        "link_bin": "https://github.com/lmbstudiocontact/mb5_3/raw/main/Boy_L6_-944583170_Spanish.bin",
        "name_language": "Spanish",
        "id_bin_language": "Boy_L6_-944583170_Spanish"
      }
    ],
    "array_tags": [
      "lmbstudio"
    ],
    "list_album": [
      {
        "id_album": "1995733213",
        "link_thumb": "https://live.staticflickr.com/65535/51695781824_9087e34b43_o.gif",
        "title": "Boy_L6"
      }
    ]
  },
  {
    "author": "shymik",
    "link_thumb": "https://live.staticflickr.com/65535/51694646594_d8a776eccd_o.gif",
    "link_bin": "https://github.com/lmbstudiocontact/mb5_12/raw/main/1016.bin",
    "id_bin": "1016",
    "list_language": [],
    "array_tags": [
      "digital",
      "date",
      "seconds",
      "distance",
      "heartrate",
      "weather",
      "calories",
      "battery",
      "steps"
    ],
    "list_album": [
      {
        "id_album": "2433880",
        "link_thumb": "https://live.staticflickr.com/65535/51694646594_d8a776eccd_o.gif",
        "title": "None"
      }
    ]
  },
  {
    "author": "sgssantos",
    "link_thumb": "https://live.staticflickr.com/65535/51694365208_dcd036d341_o.gif",
    "link_bin": "https://github.com/lmbstudiocontact/mb5_12/raw/main/1858.bin",
    "id_bin": "1858",
    "list_language": [],
    "array_tags": [
      "digital",
      "date",
      "distance",
      "heartrate",
      "weather",
      "alarm",
      "temperature",
      "battery",
      "steps"
    ],
    "list_album": [
      {
        "id_album": "2433880",
        "link_thumb": "https://live.staticflickr.com/65535/51694365208_dcd036d341_o.gif",
        "title": "None"
      }
    ]
  },
  {
    "author": "LMB Studio",
    "link_thumb": "https://live.staticflickr.com/65535/51694291572_2bd93ec6dc_o.gif",
    "link_bin": "https://github.com/lmbstudiocontact/mb5_3/raw/main/Boy_L6_-305503734.bin",
    "id_bin": "Boy_L6_-305503734",
    "list_language": [
      {
        "author": "LMB Studio",
        "link_thumb": "https://live.staticflickr.com/65535/51695359363_37795a4ac2_o.gif",
        "link_bin": "https://github.com/lmbstudiocontact/mb5_3/raw/main/Boy_L6_-305503734_English.bin",
        "name_language": "English",
        "id_bin_language": "Boy_L6_-305503734_English"
      },
      {
        "author": "LMB Studio",
        "link_thumb": "https://live.staticflickr.com/65535/51695083786_b414b7eb46_o.gif",
        "link_bin": "https://github.com/lmbstudiocontact/mb5_3/raw/main/Boy_L6_-305503734_Portuguese.bin",
        "name_language": "Portuguese",
        "id_bin_language": "Boy_L6_-305503734_Portuguese"
      },
      {
        "author": "LMB Studio",
        "link_thumb": "https://live.staticflickr.com/65535/51695765129_c511979fc6_o.gif",
        "link_bin": "https://github.com/lmbstudiocontact/mb5_3/raw/main/Boy_L6_-305503734_Russian.bin",
        "name_language": "Russian",
        "id_bin_language": "Boy_L6_-305503734_Russian"
      },
      {
        "author": "LMB Studio",
        "link_thumb": "https://live.staticflickr.com/65535/51695084691_ab39859e82_o.gif",
        "link_bin": "https://github.com/lmbstudiocontact/mb5_3/raw/main/Boy_L6_-305503734_Spanish.bin",
        "name_language": "Spanish",
        "id_bin_language": "Boy_L6_-305503734_Spanish"
      }
    ],
    "array_tags": [
      "lmbstudio"
    ],
    "list_album": [
      {
        "id_album": "1995733213",
        "link_thumb": "https://live.staticflickr.com/65535/51694291572_2bd93ec6dc_o.gif",
        "title": "Boy_L6"
      }
    ]
  },
  {
    "author": "LMB Studio",
    "link_thumb": "https://live.staticflickr.com/65535/51694301142_460afc8c69_o.gif",
    "link_bin": "https://github.com/lmbstudiocontact/mb5_3/raw/main/Boy_L6_-418159930.bin",
    "id_bin": "Boy_L6_-418159930",
    "list_language": [
      {
        "author": "LMB Studio",
        "link_thumb": "https://live.staticflickr.com/65535/51695368843_59587da2a8_o.gif",
        "link_bin": "https://github.com/lmbstudiocontact/mb5_3/raw/main/Boy_L6_-418159930_English.bin",
        "name_language": "English",
        "id_bin_language": "Boy_L6_-418159930_English"
      },
      {
        "author": "LMB Studio",
        "link_thumb": "https://live.staticflickr.com/65535/51695774009_e82ca15419_o.gif",
        "link_bin": "https://github.com/lmbstudiocontact/mb5_3/raw/main/Boy_L6_-418159930_Portuguese.bin",
        "name_language": "Portuguese",
        "id_bin_language": "Boy_L6_-418159930_Portuguese"
      },
      {
        "author": "LMB Studio",
        "link_thumb": "https://live.staticflickr.com/65535/51695369953_5d9701f66a_o.gif",
        "link_bin": "https://github.com/lmbstudiocontact/mb5_3/raw/main/Boy_L6_-418159930_Russian.bin",
        "name_language": "Russian",
        "id_bin_language": "Boy_L6_-418159930_Russian"
      },
      {
        "author": "LMB Studio",
        "link_thumb": "https://live.staticflickr.com/65535/51694302972_aa195923cd_o.gif",
        "link_bin": "https://github.com/lmbstudiocontact/mb5_3/raw/main/Boy_L6_-418159930_Spanish.bin",
        "name_language": "Spanish",
        "id_bin_language": "Boy_L6_-418159930_Spanish"
      }
    ],
    "array_tags": [
      "lmbstudio"
    ],
    "list_album": [
      {
        "id_album": "1995733213",
        "link_thumb": "https://live.staticflickr.com/65535/51694301142_460afc8c69_o.gif",
        "title": "Boy_L6"
      }
    ]
  },
  {
    "author": "LMB Studio",
    "link_thumb": "https://live.staticflickr.com/65535/51780409453_07dd147386_o.gif",
    "link_bin": "https://github.com/lmbstudiocontact/mb5_1/raw/main/BossBabyCartoon_L5_156863955.bin",
    "id_bin": "BossBabyCartoon_L5_156863955",
    "list_language": [
      {
        "author": "LMB Studio",
        "link_thumb": "https://live.staticflickr.com/65535/51779343892_4144480f70_o.gif",
        "link_bin": "https://github.com/lmbstudiocontact/mb5_1/raw/main/BossBabyCartoon_L5_156863955_English.bin",
        "name_language": "English",
        "id_bin_language": "BossBabyCartoon_L5_156863955_English"
      },
      {
        "author": "LMB Studio",
        "link_thumb": "https://live.staticflickr.com/65535/51780160516_bdc708d320_o.gif",
        "link_bin": "https://github.com/lmbstudiocontact/mb5_1/raw/main/BossBabyCartoon_L5_156863955_Portuguese.bin",
        "name_language": "Portuguese",
        "id_bin_language": "BossBabyCartoon_L5_156863955_Portuguese"
      },
      {
        "author": "LMB Studio",
        "link_thumb": "https://live.staticflickr.com/65535/51779343782_6a94656acd_o.gif",
        "link_bin": "https://github.com/lmbstudiocontact/mb5_1/raw/main/BossBabyCartoon_L5_156863955_Russian.bin",
        "name_language": "Russian",
        "id_bin_language": "BossBabyCartoon_L5_156863955_Russian"
      },
      {
        "author": "LMB Studio",
        "link_thumb": "https://live.staticflickr.com/65535/51780409283_0f8cf46f18_o.gif",
        "link_bin": "https://github.com/lmbstudiocontact/mb5_1/raw/main/BossBabyCartoon_L5_156863955_Spanish.bin",
        "name_language": "Spanish",
        "id_bin_language": "BossBabyCartoon_L5_156863955_Spanish"
      }
    ],
    "array_tags": [
      "lmbstudio"
    ],
    "list_album": [
      {
        "id_album": "158762705",
        "link_thumb": "https://live.staticflickr.com/65535/51780409453_07dd147386_o.gif",
        "title": "Boss Baby Cartoon_L5"
      }
    ]
  },
  {
    "author": "None",
    "link_thumb": "https://live.staticflickr.com/65535/51695009829_db4bc90c85_o.gif",
    "link_bin": "https://github.com/lmbstudiocontact/mb5_0/raw/main/459.bin",
    "id_bin": "459",
    "list_language": [],
    "array_tags": [],
    "list_album": [
      {
        "id_album": "2433880",
        "link_thumb": "https://live.staticflickr.com/65535/51695009829_db4bc90c85_o.gif",
        "title": "None"
      }
    ]
  },
  {
    "author": "Soul89reg",
    "link_thumb": "https://live.staticflickr.com/65535/51695014900_f2b9d909cd_o.gif",
    "link_bin": "https://github.com/lmbstudiocontact/mb5_12/raw/main/2124.bin",
    "id_bin": "2124",
    "list_language": [],
    "array_tags": [
      "digital",
      "date",
      "seconds",
      "distance",
      "heartrate",
      "calories",
      "battery",
      "steps"
    ],
    "list_album": [
      {
        "id_album": "2433880",
        "link_thumb": "https://live.staticflickr.com/65535/51695014900_f2b9d909cd_o.gif",
        "title": "None"
      }
    ]
  },
  {
    "author": "LMB Studio",
    "link_thumb": "https://live.staticflickr.com/65535/51694289502_fef1ff46c0_o.gif",
    "link_bin": "https://github.com/lmbstudiocontact/mb5_3/raw/main/Boy_L6_-239647665.bin",
    "id_bin": "Boy_L6_-239647665",
    "list_language": [
      {
        "author": "LMB Studio",
        "link_thumb": "https://live.staticflickr.com/65535/51695357173_7ae38205d1_o.gif",
        "link_bin": "https://github.com/lmbstudiocontact/mb5_3/raw/main/Boy_L6_-239647665_English.bin",
        "name_language": "English",
        "id_bin_language": "Boy_L6_-239647665_English"
      },
      {
        "author": "LMB Studio",
        "link_thumb": "https://live.staticflickr.com/65535/51695974020_b4d4ec4066_o.gif",
        "link_bin": "https://github.com/lmbstudiocontact/mb5_3/raw/main/Boy_L6_-239647665_Portuguese.bin",
        "name_language": "Portuguese",
        "id_bin_language": "Boy_L6_-239647665_Portuguese"
      },
      {
        "author": "LMB Studio",
        "link_thumb": "https://live.staticflickr.com/65535/51695358248_0eb6693c71_o.gif",
        "link_bin": "https://github.com/lmbstudiocontact/mb5_3/raw/main/Boy_L6_-239647665_Russian.bin",
        "name_language": "Russian",
        "id_bin_language": "Boy_L6_-239647665_Russian"
      },
      {
        "author": "LMB Studio",
        "link_thumb": "https://live.staticflickr.com/65535/51695082636_329290ee0a_o.gif",
        "link_bin": "https://github.com/lmbstudiocontact/mb5_3/raw/main/Boy_L6_-239647665_Spanish.bin",
        "name_language": "Spanish",
        "id_bin_language": "Boy_L6_-239647665_Spanish"
      }
    ],
    "array_tags": [
      "lmbstudio"
    ],
    "list_album": [
      {
        "id_album": "1995733213",
        "link_thumb": "https://live.staticflickr.com/65535/51694289502_fef1ff46c0_o.gif",
        "title": "Boy_L6"
      }
    ]
  },
  {
    "author": "Babbler",
    "link_thumb": "https://live.staticflickr.com/65535/51694598568_cc36740ca2_o.gif",
    "link_bin": "https://github.com/lmbstudiocontact/mb5_0/raw/main/41.bin",
    "id_bin": "41",
    "list_language": [],
    "array_tags": [
      "digital",
      "date",
      "battery",
      "steps"
    ],
    "list_album": [
      {
        "id_album": "63410260",
        "link_thumb": "https://live.staticflickr.com/65535/51694598568_cc36740ca2_o.gif",
        "title": "Anime"
      }
    ]
  },
  {
    "author": "Oliwoo",
    "link_thumb": "https://live.staticflickr.com/65535/51693591212_5ccb7e91e7_o.gif",
    "link_bin": "https://github.com/lmbstudiocontact/mb5_3/raw/main/693.bin",
    "id_bin": "693",
    "list_language": [],
    "array_tags": [
      "digital",
      "date",
      "heartrate",
      "weather",
      "battery",
      "steps"
    ],
    "list_album": [
      {
        "id_album": "2433880",
        "link_thumb": "https://live.staticflickr.com/65535/51693591212_5ccb7e91e7_o.gif",
        "title": "None"
      }
    ]
  },
  {
    "author": "awrun",
    "link_thumb": "https://live.staticflickr.com/65535/51694853699_476a61e444_o.gif",
    "link_bin": "https://github.com/lmbstudiocontact/mb5_0/raw/main/268.bin",
    "id_bin": "268",
    "list_language": [],
    "array_tags": [
      "digital",
      "date",
      "heartrate",
      "weather",
      "humidity",
      "battery",
      "steps",
      "wind"
    ],
    "list_album": [
      {
        "id_album": "2433880",
        "link_thumb": "https://live.staticflickr.com/65535/51694853699_476a61e444_o.gif",
        "title": "None"
      }
    ]
  },
  {
    "author": "LMB Studio",
    "link_thumb": "https://live.staticflickr.com/65535/51695375248_1d5bd6ffb8_o.gif",
    "link_bin": "https://github.com/lmbstudiocontact/mb5_3/raw/main/Boy_L6_-944582454.bin",
    "id_bin": "Boy_L6_-944582454",
    "list_language": [
      {
        "author": "LMB Studio",
        "link_thumb": "https://live.staticflickr.com/65535/51695099406_f285e04164_o.gif",
        "link_bin": "https://github.com/lmbstudiocontact/mb5_3/raw/main/Boy_L6_-944582454_English.bin",
        "name_language": "English",
        "id_bin_language": "Boy_L6_-944582454_English"
      },
      {
        "author": "LMB Studio",
        "link_thumb": "https://live.staticflickr.com/65535/51695780449_6605a64943_o.gif",
        "link_bin": "https://github.com/lmbstudiocontact/mb5_3/raw/main/Boy_L6_-944582454_Portuguese.bin",
        "name_language": "Portuguese",
        "id_bin_language": "Boy_L6_-944582454_Portuguese"
      },
      {
        "author": "LMB Studio",
        "link_thumb": "https://live.staticflickr.com/65535/51695100276_b55b399a8f_o.gif",
        "link_bin": "https://github.com/lmbstudiocontact/mb5_3/raw/main/Boy_L6_-944582454_Russian.bin",
        "name_language": "Russian",
        "id_bin_language": "Boy_L6_-944582454_Russian"
      },
      {
        "author": "LMB Studio",
        "link_thumb": "https://live.staticflickr.com/65535/51695992765_24d08f8b9f_o.gif",
        "link_bin": "https://github.com/lmbstudiocontact/mb5_3/raw/main/Boy_L6_-944582454_Spanish.bin",
        "name_language": "Spanish",
        "id_bin_language": "Boy_L6_-944582454_Spanish"
      }
    ],
    "array_tags": [
      "lmbstudio"
    ],
    "list_album": [
      {
        "id_album": "1995733213",
        "link_thumb": "https://live.staticflickr.com/65535/51695375248_1d5bd6ffb8_o.gif",
        "title": "Boy_L6"
      }
    ]
  },
  {
    "author": "lucasvinisk8",
    "link_thumb": "https://live.staticflickr.com/65535/51695045220_00e473dced_o.gif",
    "link_bin": "https://github.com/lmbstudiocontact/mb5_22/raw/main/2487.bin",
    "id_bin": "2487",
    "list_language": [],
    "array_tags": [
      "naruto",
      "anime"
    ],
    "list_album": [
      {
        "id_album": "63410260",
        "link_thumb": "https://live.staticflickr.com/65535/51695045220_00e473dced_o.gif",
        "title": "Anime"
      }
    ]
  },
  {
    "author": "WantonFlyer",
    "link_thumb": "https://live.staticflickr.com/65535/51694411793_0cc2fb2e90_o.gif",
    "link_bin": "https://github.com/lmbstudiocontact/mb5_12/raw/main/2244.bin",
    "id_bin": "2244",
    "list_language": [],
    "array_tags": [
      "digital",
      "date",
      "distance",
      "heartrate",
      "weather",
      "calories",
      "battery",
      "steps"
    ],
    "list_album": [
      {
        "id_album": "2433880",
        "link_thumb": "https://live.staticflickr.com/65535/51694411793_0cc2fb2e90_o.gif",
        "title": "None"
      }
    ]
  },
  {
    "author": "useooo01",
    "link_thumb": "https://live.staticflickr.com/65535/51694668429_0317cd8714_o.gif",
    "link_bin": "https://github.com/lmbstudiocontact/mb5_12/raw/main/1171.bin",
    "id_bin": "1171",
    "list_language": [],
    "array_tags": [
      "date",
      "digital",
      "battery"
    ],
    "list_album": [
      {
        "id_album": "2433880",
        "link_thumb": "https://live.staticflickr.com/65535/51694668429_0317cd8714_o.gif",
        "title": "None"
      }
    ]
  },
  {
    "author": "Eliud",
    "link_thumb": "https://live.staticflickr.com/65535/51693312722_4d2b683bb6_o.gif",
    "link_bin": "https://github.com/lmbstudiocontact/mb5_12/raw/main/1949.bin",
    "id_bin": "1949",
    "list_language": [],
    "array_tags": [
      "watchface",
      "miband5"
    ],
    "list_album": [
      {
        "id_album": "2433880",
        "link_thumb": "https://live.staticflickr.com/65535/51693312722_4d2b683bb6_o.gif",
        "title": "None"
      }
    ]
  },
  {
    "author": "None",
    "link_thumb": "https://live.staticflickr.com/65535/51695127485_5aa843f173_o.gif",
    "link_bin": "https://github.com/lmbstudiocontact/mb5_0/raw/main/31_fix.bin",
    "id_bin": "31_fix",
    "list_language": [],
    "array_tags": [],
    "list_album": [
      {
        "id_album": "63410260",
        "link_thumb": "https://live.staticflickr.com/65535/51695127485_5aa843f173_o.gif",
        "title": "Anime"
      }
    ]
  },
  {
    "author": "None",
    "link_thumb": "https://live.staticflickr.com/65535/51700943130_623edc482b_o.gif",
    "link_bin": "https://github.com/lmbstudiocontact/mb5_38/raw/main/M0046.bin",
    "id_bin": "M0046",
    "list_language": [
      {
        "author": "None",
        "link_thumb": "https://live.staticflickr.com/65535/51700334923_1fe453bd8d_o.gif",
        "link_bin": "https://github.com/lmbstudiocontact/mb5_38/raw/main/M0046_English.bin",
        "name_language": "English",
        "id_bin_language": "M0046_English"
      },
      {
        "author": "None",
        "link_thumb": "https://live.staticflickr.com/65535/51700731634_e3eaecc26b_o.gif",
        "link_bin": "https://github.com/lmbstudiocontact/mb5_38/raw/main/M0046_Portuguese.bin",
        "name_language": "Portuguese",
        "id_bin_language": "M0046_Portuguese"
      },
      {
        "author": "None",
        "link_thumb": "https://live.staticflickr.com/65535/51700057716_9e36978a1b_o.gif",
        "link_bin": "https://github.com/lmbstudiocontact/mb5_38/raw/main/M0046_Russian.bin",
        "name_language": "Russian",
        "id_bin_language": "M0046_Russian"
      },
      {
        "author": "None",
        "link_thumb": "https://live.staticflickr.com/65535/51699260827_e089f80401_o.gif",
        "link_bin": "https://github.com/lmbstudiocontact/mb5_38/raw/main/M0046_Spanish.bin",
        "name_language": "Spanish",
        "id_bin_language": "M0046_Spanish"
      }
    ],
    "array_tags": [],
    "list_album": [
      {
        "id_album": "-583089738",
        "link_thumb": "https://live.staticflickr.com/65535/51700943130_623edc482b_o.gif",
        "title": "Mifit Store"
      }
    ]
  },
  {
    "author": "vuong205",
    "link_thumb": "https://live.staticflickr.com/65535/51694671119_7851c9d422_o.gif",
    "link_bin": "https://github.com/lmbstudiocontact/mb5_12/raw/main/1199.bin",
    "id_bin": "1199",
    "list_language": [],
    "array_tags": [
      "digital",
      "date",
      "heartrate",
      "weather",
      "battery",
      "steps"
    ],
    "list_album": [
      {
        "id_album": "2433880",
        "link_thumb": "https://live.staticflickr.com/65535/51694671119_7851c9d422_o.gif",
        "title": "None"
      }
    ]
  },
  {
    "author": "LMB Studio",
    "link_thumb": "https://live.staticflickr.com/65535/51694299102_5ce5231e54_o.gif",
    "link_bin": "https://github.com/lmbstudiocontact/mb5_3/raw/main/Boy_L6_-418159926.bin",
    "id_bin": "Boy_L6_-418159926",
    "list_language": [
      {
        "author": "LMB Studio",
        "link_thumb": "https://live.staticflickr.com/65535/51695366503_c9718363a1_o.gif",
        "link_bin": "https://github.com/lmbstudiocontact/mb5_3/raw/main/Boy_L6_-418159926_English.bin",
        "name_language": "English",
        "id_bin_language": "Boy_L6_-418159926_English"
      },
      {
        "author": "LMB Studio",
        "link_thumb": "https://live.staticflickr.com/65535/51694299942_0d012a75e5_o.gif",
        "link_bin": "https://github.com/lmbstudiocontact/mb5_3/raw/main/Boy_L6_-418159926_Portuguese.bin",
        "name_language": "Portuguese",
        "id_bin_language": "Boy_L6_-418159926_Portuguese"
      },
      {
        "author": "LMB Studio",
        "link_thumb": "https://live.staticflickr.com/65535/51695367548_2421f088c9_o.gif",
        "link_bin": "https://github.com/lmbstudiocontact/mb5_3/raw/main/Boy_L6_-418159926_Russian.bin",
        "name_language": "Russian",
        "id_bin_language": "Boy_L6_-418159926_Russian"
      },
      {
        "author": "LMB Studio",
        "link_thumb": "https://live.staticflickr.com/65535/51695772749_bd66301159_o.gif",
        "link_bin": "https://github.com/lmbstudiocontact/mb5_3/raw/main/Boy_L6_-418159926_Spanish.bin",
        "name_language": "Spanish",
        "id_bin_language": "Boy_L6_-418159926_Spanish"
      }
    ],
    "array_tags": [
      "lmbstudio"
    ],
    "list_album": [
      {
        "id_album": "1995733213",
        "link_thumb": "https://live.staticflickr.com/65535/51694299102_5ce5231e54_o.gif",
        "title": "Boy_L6"
      }
    ]
  },
  {
    "author": "ahidzatx",
    "link_thumb": "https://live.staticflickr.com/65535/51693620862_0309b2e9de_o.gif",
    "link_bin": "https://github.com/lmbstudiocontact/mb5_3/raw/main/844.bin",
    "id_bin": "844",
    "list_language": [],
    "array_tags": [
      "digital",
      "date",
      "seconds",
      "distance",
      "heartrate",
      "weather",
      "calories",
      "battery",
      "steps"
    ],
    "list_album": [
      {
        "id_album": "2433880",
        "link_thumb": "https://live.staticflickr.com/65535/51693620862_0309b2e9de_o.gif",
        "title": "None"
      }
    ]
  },
  {
    "author": "shymik",
    "link_thumb": "https://live.staticflickr.com/65535/51694681669_e58942774f_o.gif",
    "link_bin": "https://github.com/lmbstudiocontact/mb5_12/raw/main/1270.bin",
    "id_bin": "1270",
    "list_language": [],
    "array_tags": [
      "digital",
      "date",
      "distance",
      "heartrate",
      "weather",
      "calories",
      "battery",
      "steps"
    ],
    "list_album": [
      {
        "id_album": "2433880",
        "link_thumb": "https://live.staticflickr.com/65535/51694681669_e58942774f_o.gif",
        "title": "None"
      }
    ]
  },
  {
    "author": "cedL02",
    "link_thumb": "https://live.staticflickr.com/65535/51694146666_3ec6856543_o.gif",
    "link_bin": "https://github.com/lmbstudiocontact/mb5_12/raw/main/2344.bin",
    "id_bin": "2344",
    "list_language": [],
    "array_tags": [
      "date",
      "distance",
      "animated",
      "manga",
      "steps",
      "day",
      "anime"
    ],
    "list_album": [
      {
        "id_album": "63410260",
        "link_thumb": "https://live.staticflickr.com/65535/51694146666_3ec6856543_o.gif",
        "title": "Anime"
      }
    ]
  },
  {
    "author": "donjohrian",
    "link_thumb": "https://live.staticflickr.com/65535/51693653727_1c2eaaed2e_o.gif",
    "link_bin": "https://github.com/lmbstudiocontact/mb5_23/raw/main/998.bin",
    "id_bin": "998",
    "list_language": [],
    "array_tags": [
      "date",
      "analog",
      "minimal",
      "time"
    ],
    "list_album": [
      {
        "id_album": "2433880",
        "link_thumb": "https://live.staticflickr.com/65535/51693653727_1c2eaaed2e_o.gif",
        "title": "None"
      }
    ]
  },
  {
    "author": "shymik",
    "link_thumb": "https://live.staticflickr.com/65535/51693346812_dd737ab744_o.gif",
    "link_bin": "https://github.com/lmbstudiocontact/mb5_12/raw/main/2274.bin",
    "id_bin": "2274",
    "list_language": [],
    "array_tags": [
      "digital",
      "date",
      "distance",
      "heartrate",
      "weather",
      "battery",
      "steps"
    ],
    "list_album": [
      {
        "id_album": "2433880",
        "link_thumb": "https://live.staticflickr.com/65535/51693346812_dd737ab744_o.gif",
        "title": "None"
      }
    ]
  },
  {
    "author": "None",
    "link_thumb": "https://live.staticflickr.com/65535/51695022829_f105830d5b_o.gif",
    "link_bin": "https://github.com/lmbstudiocontact/mb5_0/raw/main/511.bin",
    "id_bin": "511",
    "list_language": [],
    "array_tags": [],
    "list_album": [
      {
        "id_album": "2433880",
        "link_thumb": "https://live.staticflickr.com/65535/51695022829_f105830d5b_o.gif",
        "title": "None"
      }
    ]
  },
  {
    "author": "LMB Studio",
    "link_thumb": "https://live.staticflickr.com/65535/51780801329_44dd88595f_o.gif",
    "link_bin": "https://github.com/lmbstudiocontact/mb5_1/raw/main/BossBabyCartoon_L5_446268251.bin",
    "id_bin": "BossBabyCartoon_L5_446268251",
    "list_language": [
      {
        "author": "LMB Studio",
        "link_thumb": "https://live.staticflickr.com/65535/51781043530_6720d4ce21_o.gif",
        "link_bin": "https://github.com/lmbstudiocontact/mb5_1/raw/main/BossBabyCartoon_L5_446268251_English.bin",
        "name_language": "English",
        "id_bin_language": "BossBabyCartoon_L5_446268251_English"
      },
      {
        "author": "LMB Studio",
        "link_thumb": "https://live.staticflickr.com/65535/51780160131_2487ce1b10_o.gif",
        "link_bin": "https://github.com/lmbstudiocontact/mb5_1/raw/main/BossBabyCartoon_L5_446268251_Portuguese.bin",
        "name_language": "Portuguese",
        "id_bin_language": "BossBabyCartoon_L5_446268251_Portuguese"
      },
      {
        "author": "LMB Studio",
        "link_thumb": "https://live.staticflickr.com/65535/51780160096_8505fee3b8_o.gif",
        "link_bin": "https://github.com/lmbstudiocontact/mb5_1/raw/main/BossBabyCartoon_L5_446268251_Russian.bin",
        "name_language": "Russian",
        "id_bin_language": "BossBabyCartoon_L5_446268251_Russian"
      },
      {
        "author": "LMB Studio",
        "link_thumb": "https://live.staticflickr.com/65535/51780160041_2e12e815d2_o.gif",
        "link_bin": "https://github.com/lmbstudiocontact/mb5_1/raw/main/BossBabyCartoon_L5_446268251_Spanish.bin",
        "name_language": "Spanish",
        "id_bin_language": "BossBabyCartoon_L5_446268251_Spanish"
      }
    ],
    "array_tags": [
      "lmbstudio"
    ],
    "list_album": [
      {
        "id_album": "158762705",
        "link_thumb": "https://live.staticflickr.com/65535/51780801329_44dd88595f_o.gif",
        "title": "Boss Baby Cartoon_L5"
      }
    ]
  },
  {
    "author": "PaTRiKa871",
    "link_thumb": "https://live.staticflickr.com/65535/51693992996_0137243e95_o.gif",
    "link_bin": "https://github.com/lmbstudiocontact/mb5_12/raw/main/1173.bin",
    "id_bin": "1173",
    "list_language": [],
    "array_tags": [
      "digital",
      "date",
      "battery",
      "steps"
    ],
    "list_album": [
      {
        "id_album": "2433880",
        "link_thumb": "https://live.staticflickr.com/65535/51693992996_0137243e95_o.gif",
        "title": "None"
      }
    ]
  },
  {
    "author": "LMB Studio",
    "link_thumb": "https://live.staticflickr.com/65535/51695666358_784a0c48e2_o.gif",
    "link_bin": "https://github.com/lmbstudiocontact/mb5_27/raw/main/Cat_L6_-525203852.bin",
    "id_bin": "Cat_L6_-525203852",
    "list_language": [
      {
        "author": "LMB Studio",
        "link_thumb": "https://live.staticflickr.com/65535/51696281780_0ddf767d41_o.gif",
        "link_bin": "https://github.com/lmbstudiocontact/mb5_27/raw/main/Cat_L6_-525203852_English.bin",
        "name_language": "English",
        "id_bin_language": "Cat_L6_-525203852_English"
      },
      {
        "author": "LMB Studio",
        "link_thumb": "https://live.staticflickr.com/65535/51696069944_178aea1d80_o.gif",
        "link_bin": "https://github.com/lmbstudiocontact/mb5_27/raw/main/Cat_L6_-525203852_Portuguese.bin",
        "name_language": "Portuguese",
        "id_bin_language": "Cat_L6_-525203852_Portuguese"
      },
      {
        "author": "LMB Studio",
        "link_thumb": "https://live.staticflickr.com/65535/51695389126_6017b69938_o.gif",
        "link_bin": "https://github.com/lmbstudiocontact/mb5_27/raw/main/Cat_L6_-525203852_Russian.bin",
        "name_language": "Russian",
        "id_bin_language": "Cat_L6_-525203852_Russian"
      },
      {
        "author": "LMB Studio",
        "link_thumb": "https://live.staticflickr.com/65535/51695389446_7f4882d92e_o.gif",
        "link_bin": "https://github.com/lmbstudiocontact/mb5_27/raw/main/Cat_L6_-525203852_Spanish.bin",
        "name_language": "Spanish",
        "id_bin_language": "Cat_L6_-525203852_Spanish"
      }
    ],
    "array_tags": [
      "lmbstudio"
    ],
    "list_album": [
      {
        "id_album": "2011284115",
        "link_thumb": "https://live.staticflickr.com/65535/51695666358_784a0c48e2_o.gif",
        "title": "Cat_L6"
      }
    ]
  },
  {
    "author": "LMB Studio",
    "link_thumb": "https://live.staticflickr.com/65535/51695370663_cdc0e8f54a_o.gif",
    "link_bin": "https://github.com/lmbstudiocontact/mb5_3/raw/main/Boy_L6_-418159958.bin",
    "id_bin": "Boy_L6_-418159958",
    "list_language": [
      {
        "author": "LMB Studio",
        "link_thumb": "https://live.staticflickr.com/65535/51695095161_b11ddae16d_o.gif",
        "link_bin": "https://github.com/lmbstudiocontact/mb5_3/raw/main/Boy_L6_-418159958_English.bin",
        "name_language": "English",
        "id_bin_language": "Boy_L6_-418159958_English"
      },
      {
        "author": "LMB Studio",
        "link_thumb": "https://live.staticflickr.com/65535/51695095636_a9bfd106a2_o.gif",
        "link_bin": "https://github.com/lmbstudiocontact/mb5_3/raw/main/Boy_L6_-418159958_Portuguese.bin",
        "name_language": "Portuguese",
        "id_bin_language": "Boy_L6_-418159958_Portuguese"
      },
      {
        "author": "LMB Studio",
        "link_thumb": "https://live.staticflickr.com/65535/51695096176_b71eba8d02_o.gif",
        "link_bin": "https://github.com/lmbstudiocontact/mb5_3/raw/main/Boy_L6_-418159958_Russian.bin",
        "name_language": "Russian",
        "id_bin_language": "Boy_L6_-418159958_Russian"
      },
      {
        "author": "LMB Studio",
        "link_thumb": "https://live.staticflickr.com/65535/51695372783_f76d8e54b7_o.gif",
        "link_bin": "https://github.com/lmbstudiocontact/mb5_3/raw/main/Boy_L6_-418159958_Spanish.bin",
        "name_language": "Spanish",
        "id_bin_language": "Boy_L6_-418159958_Spanish"
      }
    ],
    "array_tags": [
      "lmbstudio"
    ],
    "list_album": [
      {
        "id_album": "1995733213",
        "link_thumb": "https://live.staticflickr.com/65535/51695370663_cdc0e8f54a_o.gif",
        "title": "Boy_L6"
      }
    ]
  },
  {
    "author": "Crypto1",
    "link_thumb": "https://live.staticflickr.com/65535/51694990755_1f00d59abc_o.gif",
    "link_bin": "https://github.com/lmbstudiocontact/mb5_12/raw/main/1926.bin",
    "id_bin": "1926",
    "list_language": [],
    "array_tags": [
      "gif",
      "animation"
    ],
    "list_album": [
      {
        "id_album": "2433880",
        "link_thumb": "https://live.staticflickr.com/65535/51694990755_1f00d59abc_o.gif",
        "title": "None"
      }
    ]
  },
  {
    "author": "LMB Studio",
    "link_thumb": "https://live.staticflickr.com/65535/51694311687_6baa42292e_o.gif",
    "link_bin": "https://github.com/lmbstudiocontact/mb5_3/raw/main/Boy_L6_-944583198.bin",
    "id_bin": "Boy_L6_-944583198",
    "list_language": [
      {
        "author": "LMB Studio",
        "link_thumb": "https://live.staticflickr.com/65535/51694312172_d931b6f32b_o.gif",
        "link_bin": "https://github.com/lmbstudiocontact/mb5_3/raw/main/Boy_L6_-944583198_English.bin",
        "name_language": "English",
        "id_bin_language": "Boy_L6_-944583198_English"
      },
      {
        "author": "LMB Studio",
        "link_thumb": "https://live.staticflickr.com/65535/51694312632_8d62bb3142_o.gif",
        "link_bin": "https://github.com/lmbstudiocontact/mb5_3/raw/main/Boy_L6_-944583198_Portuguese.bin",
        "name_language": "Portuguese",
        "id_bin_language": "Boy_L6_-944583198_Portuguese"
      },
      {
        "author": "LMB Studio",
        "link_thumb": "https://live.staticflickr.com/65535/51695380868_2e078cf5ca_o.gif",
        "link_bin": "https://github.com/lmbstudiocontact/mb5_3/raw/main/Boy_L6_-944583198_Russian.bin",
        "name_language": "Russian",
        "id_bin_language": "Boy_L6_-944583198_Russian"
      },
      {
        "author": "LMB Studio",
        "link_thumb": "https://live.staticflickr.com/65535/51695785529_593c41feb1_o.gif",
        "link_bin": "https://github.com/lmbstudiocontact/mb5_3/raw/main/Boy_L6_-944583198_Spanish.bin",
        "name_language": "Spanish",
        "id_bin_language": "Boy_L6_-944583198_Spanish"
      }
    ],
    "array_tags": [
      "lmbstudio"
    ],
    "list_album": [
      {
        "id_album": "1995733213",
        "link_thumb": "https://live.staticflickr.com/65535/51694311687_6baa42292e_o.gif",
        "title": "Boy_L6"
      }
    ]
  },
  {
    "author": "shymik",
    "link_thumb": "https://live.staticflickr.com/65535/51694070056_1b387d1ea1_o.gif",
    "link_bin": "https://github.com/lmbstudiocontact/mb5_12/raw/main/1682.bin",
    "id_bin": "1682",
    "list_language": [],
    "array_tags": [
      "digital",
      "date",
      "floors",
      "distance",
      "heartrate",
      "weather",
      "calories",
      "battery",
      "steps"
    ],
    "list_album": [
      {
        "id_album": "2433880",
        "link_thumb": "https://live.staticflickr.com/65535/51694070056_1b387d1ea1_o.gif",
        "title": "None"
      }
    ]
  },
  {
    "author": "None",
    "link_thumb": "https://live.staticflickr.com/65535/51700336683_9e277df715_o.gif",
    "link_bin": "https://github.com/lmbstudiocontact/mb5_38/raw/main/M0048.bin",
    "id_bin": "M0048",
    "list_language": [
      {
        "author": "None",
        "link_thumb": "https://live.staticflickr.com/65535/51700337278_2808f1965e_o.gif",
        "link_bin": "https://github.com/lmbstudiocontact/mb5_38/raw/main/M0048_English.bin",
        "name_language": "English",
        "id_bin_language": "M0048_English"
      },
      {
        "author": "None",
        "link_thumb": "https://live.staticflickr.com/65535/51700059501_3f8b65390d_o.gif",
        "link_bin": "https://github.com/lmbstudiocontact/mb5_38/raw/main/M0048_Portuguese.bin",
        "name_language": "Portuguese",
        "id_bin_language": "M0048_Portuguese"
      },
      {
        "author": "None",
        "link_thumb": "https://live.staticflickr.com/65535/51700059781_5a28587da6_o.gif",
        "link_bin": "https://github.com/lmbstudiocontact/mb5_38/raw/main/M0048_Russian.bin",
        "name_language": "Russian",
        "id_bin_language": "M0048_Russian"
      },
      {
        "author": "None",
        "link_thumb": "https://live.staticflickr.com/65535/51700060351_7f9bd5922e_o.gif",
        "link_bin": "https://github.com/lmbstudiocontact/mb5_38/raw/main/M0048_Spanish.bin",
        "name_language": "Spanish",
        "id_bin_language": "M0048_Spanish"
      }
    ],
    "array_tags": [],
    "list_album": [
      {
        "id_album": "-583089738",
        "link_thumb": "https://live.staticflickr.com/65535/51700336683_9e277df715_o.gif",
        "title": "Mifit Store"
      }
    ]
  },
  {
    "author": "None",
    "link_thumb": "https://live.staticflickr.com/65535/51700058361_379e56f5fb_o.gif",
    "link_bin": "https://github.com/lmbstudiocontact/mb5_38/raw/main/M0047.bin",
    "id_bin": "M0047",
    "list_language": [],
    "array_tags": [],
    "list_album": [
      {
        "id_album": "-583089738",
        "link_thumb": "https://live.staticflickr.com/65535/51700058361_379e56f5fb_o.gif",
        "title": "Mifit Store"
      }
    ]
  },
  {
    "author": "Eliud",
    "link_thumb": "https://live.staticflickr.com/65535/51694770204_ceef2e9275_o.gif",
    "link_bin": "https://github.com/lmbstudiocontact/mb5_12/raw/main/1867.bin",
    "id_bin": "1867",
    "list_language": [],
    "array_tags": [
      "watchface",
      "miband5"
    ],
    "list_album": [
      {
        "id_album": "2433880",
        "link_thumb": "https://live.staticflickr.com/65535/51694770204_ceef2e9275_o.gif",
        "title": "None"
      }
    ]
  },
  {
    "author": "ama3ing",
    "link_thumb": "https://live.staticflickr.com/65535/51695235275_d16c61684f_o.gif",
    "link_bin": "https://github.com/lmbstudiocontact/mb5_0/raw/main/519.bin",
    "id_bin": "519",
    "list_language": [],
    "array_tags": [
      "digital",
      "date",
      "distance",
      "heartrate",
      "weather",
      "calories",
      "battery",
      "steps"
    ],
    "list_album": [
      {
        "id_album": "2433880",
        "link_thumb": "https://live.staticflickr.com/65535/51695235275_d16c61684f_o.gif",
        "title": "None"
      }
    ]
  },
  {
    "author": "reda8",
    "link_thumb": "https://live.staticflickr.com/65535/51695032764_2c80023fef_o.gif",
    "link_bin": "https://github.com/lmbstudiocontact/mb5_0/raw/main/561.bin",
    "id_bin": "561",
    "list_language": [],
    "array_tags": [
      "digital",
      "date",
      "distance",
      "heartrate",
      "weather",
      "calories",
      "battery",
      "steps"
    ],
    "list_album": [
      {
        "id_album": "2433880",
        "link_thumb": "https://live.staticflickr.com/65535/51695032764_2c80023fef_o.gif",
        "title": "None"
      }
    ]
  },
  {
    "author": "None",
    "link_thumb": "https://live.staticflickr.com/65535/51694592098_c918b7e2a3_o.gif",
    "link_bin": "https://github.com/lmbstudiocontact/mb5_0/raw/main/387.bin",
    "id_bin": "387",
    "list_language": [],
    "array_tags": [],
    "list_album": [
      {
        "id_album": "2433880",
        "link_thumb": "https://live.staticflickr.com/65535/51694592098_c918b7e2a3_o.gif",
        "title": "None"
      }
    ]
  },
  {
    "author": "LMB Studio",
    "link_thumb": "https://live.staticflickr.com/65535/51694313552_a128bdab01_o.gif",
    "link_bin": "https://github.com/lmbstudiocontact/mb5_3/raw/main/Boy_L6_-988175456.bin",
    "id_bin": "Boy_L6_-988175456",
    "list_language": [
      {
        "author": "LMB Studio",
        "link_thumb": "https://live.staticflickr.com/65535/51695786344_7bf7710714_o.gif",
        "link_bin": "https://github.com/lmbstudiocontact/mb5_3/raw/main/Boy_L6_-988175456_English.bin",
        "name_language": "English",
        "id_bin_language": "Boy_L6_-988175456_English"
      },
      {
        "author": "LMB Studio",
        "link_thumb": "https://live.staticflickr.com/65535/51695382433_817bec96b2_o.gif",
        "link_bin": "https://github.com/lmbstudiocontact/mb5_3/raw/main/Boy_L6_-988175456_Portuguese.bin",
        "name_language": "Portuguese",
        "id_bin_language": "Boy_L6_-988175456_Portuguese"
      },
      {
        "author": "LMB Studio",
        "link_thumb": "https://live.staticflickr.com/65535/51695998395_3ab60d4295_o.gif",
        "link_bin": "https://github.com/lmbstudiocontact/mb5_3/raw/main/Boy_L6_-988175456_Russian.bin",
        "name_language": "Russian",
        "id_bin_language": "Boy_L6_-988175456_Russian"
      },
      {
        "author": "LMB Studio",
        "link_thumb": "https://live.staticflickr.com/65535/51694315247_3479d5bf78_o.gif",
        "link_bin": "https://github.com/lmbstudiocontact/mb5_3/raw/main/Boy_L6_-988175456_Spanish.bin",
        "name_language": "Spanish",
        "id_bin_language": "Boy_L6_-988175456_Spanish"
      }
    ],
    "array_tags": [
      "lmbstudio"
    ],
    "list_album": [
      {
        "id_album": "1995733213",
        "link_thumb": "https://live.staticflickr.com/65535/51694313552_a128bdab01_o.gif",
        "title": "Boy_L6"
      }
    ]
  },
  {
    "author": "weihaooo",
    "link_thumb": "https://live.staticflickr.com/65535/51694050631_36e4db6706_o.gif",
    "link_bin": "https://github.com/lmbstudiocontact/mb5_12/raw/main/1521.bin",
    "id_bin": "1521",
    "list_language": [],
    "array_tags": [
      "digital",
      "date",
      "steps"
    ],
    "list_album": [
      {
        "id_album": "2433880",
        "link_thumb": "https://live.staticflickr.com/65535/51694050631_36e4db6706_o.gif",
        "title": "None"
      }
    ]
  },
  {
    "author": "sgssantos",
    "link_thumb": "https://live.staticflickr.com/65535/51693288687_d33f1f3ef0_o.gif",
    "link_bin": "https://github.com/lmbstudiocontact/mb5_12/raw/main/1773.bin",
    "id_bin": "1773",
    "list_language": [],
    "array_tags": [
      "digital",
      "date",
      "heartrate",
      "weather",
      "battery",
      "steps"
    ],
    "list_album": [
      {
        "id_album": "2433880",
        "link_thumb": "https://live.staticflickr.com/65535/51693288687_d33f1f3ef0_o.gif",
        "title": "None"
      }
    ]
  },
  {
    "author": "Hojos",
    "link_thumb": "https://live.staticflickr.com/65535/51693341982_9fd020411b_o.gif",
    "link_bin": "https://github.com/lmbstudiocontact/mb5_12/raw/main/2206.bin",
    "id_bin": "2206",
    "list_language": [],
    "array_tags": [
      "digital",
      "date",
      "heartrate",
      "weather",
      "battery",
      "steps"
    ],
    "list_album": [
      {
        "id_album": "2433880",
        "link_thumb": "https://live.staticflickr.com/65535/51693341982_9fd020411b_o.gif",
        "title": "None"
      }
    ]
  },
  {
    "author": "None",
    "link_thumb": "https://live.staticflickr.com/65535/51700950670_ac5ef86c47_o.gif",
    "link_bin": "https://github.com/lmbstudiocontact/mb5_38/raw/main/M0051.bin",
    "id_bin": "M0051",
    "list_language": [
      {
        "author": "None",
        "link_thumb": "https://live.staticflickr.com/65535/51700951055_08fa82f4ba_o.gif",
        "link_bin": "https://github.com/lmbstudiocontact/mb5_38/raw/main/M0051_English.bin",
        "name_language": "English",
        "id_bin_language": "M0051_English"
      },
      {
        "author": "None",
        "link_thumb": "https://live.staticflickr.com/65535/51700064486_a4f3b45408_o.gif",
        "link_bin": "https://github.com/lmbstudiocontact/mb5_38/raw/main/M0051_Portuguese.bin",
        "name_language": "Portuguese",
        "id_bin_language": "M0051_Portuguese"
      },
      {
        "author": "None",
        "link_thumb": "https://live.staticflickr.com/65535/51700342438_8cc25fbd8c_o.gif",
        "link_bin": "https://github.com/lmbstudiocontact/mb5_38/raw/main/M0051_Russian.bin",
        "name_language": "Russian",
        "id_bin_language": "M0051_Russian"
      },
      {
        "author": "None",
        "link_thumb": "https://live.staticflickr.com/65535/51700739624_e0c8cebf78_o.gif",
        "link_bin": "https://github.com/lmbstudiocontact/mb5_38/raw/main/M0051_Spanish.bin",
        "name_language": "Spanish",
        "id_bin_language": "M0051_Spanish"
      }
    ],
    "array_tags": [],
    "list_album": [
      {
        "id_album": "-583089738",
        "link_thumb": "https://live.staticflickr.com/65535/51700950670_ac5ef86c47_o.gif",
        "title": "Mifit Store"
      }
    ]
  },
  {
    "author": "None",
    "link_thumb": "https://live.staticflickr.com/65535/51700060706_fa197c057c_o.gif",
    "link_bin": "https://github.com/lmbstudiocontact/mb5_38/raw/main/M0049.bin",
    "id_bin": "M0049",
    "list_language": [
      {
        "author": "None",
        "link_thumb": "https://live.staticflickr.com/65535/51700735514_e48a386813_o.gif",
        "link_bin": "https://github.com/lmbstudiocontact/mb5_38/raw/main/M0049_English.bin",
        "name_language": "English",
        "id_bin_language": "M0049_English"
      },
      {
        "author": "None",
        "link_thumb": "https://live.staticflickr.com/65535/51700061411_809b2f9567_o.gif",
        "link_bin": "https://github.com/lmbstudiocontact/mb5_38/raw/main/M0049_Portuguese.bin",
        "name_language": "Portuguese",
        "id_bin_language": "M0049_Portuguese"
      },
      {
        "author": "None",
        "link_thumb": "https://live.staticflickr.com/65535/51700061786_b1f00d651b_o.gif",
        "link_bin": "https://github.com/lmbstudiocontact/mb5_38/raw/main/M0049_Russian.bin",
        "name_language": "Russian",
        "id_bin_language": "M0049_Russian"
      },
      {
        "author": "None",
        "link_thumb": "https://live.staticflickr.com/65535/51700736774_a9a6a7dc58_o.gif",
        "link_bin": "https://github.com/lmbstudiocontact/mb5_38/raw/main/M0049_Spanish.bin",
        "name_language": "Spanish",
        "id_bin_language": "M0049_Spanish"
      }
    ],
    "array_tags": [],
    "list_album": [
      {
        "id_album": "-583089738",
        "link_thumb": "https://live.staticflickr.com/65535/51700060706_fa197c057c_o.gif",
        "title": "Mifit Store"
      }
    ]
  }
]