[
  {
    "author": "Babbler",
    "link_thumb": "https://live.staticflickr.com/65535/51694598568_cc36740ca2_o.gif",
    "link_bin": "https://github.com/lmbstudiocontact/mb5_0/raw/main/41.bin",
    "id_bin": "41",
    "list_language": [],
    "array_tags": [
      "digital",
      "date",
      "battery",
      "steps"
    ],
    "list_album": [
      {
        "id_album": "63410260",
        "link_thumb": "https://live.staticflickr.com/65535/51694598568_cc36740ca2_o.gif",
        "title": "Anime"
      }
    ]
  },
  {
    "author": "Orange12",
    "link_thumb": "https://live.staticflickr.com/65535/51693343227_0117e547f8_o.gif",
    "link_bin": "https://github.com/lmbstudiocontact/mb5_0/raw/main/222.bin",
    "id_bin": "222",
    "list_language": [],
    "array_tags": [
      "weather"
    ],
    "list_album": [
      {
        "id_album": "2433880",
        "link_thumb": "https://live.staticflickr.com/65535/51693343227_0117e547f8_o.gif",
        "title": "None"
      }
    ]
  },
  {
    "author": "LMB Studio",
    "link_thumb": "https://live.staticflickr.com/65535/51780409453_07dd147386_o.gif",
    "link_bin": "https://github.com/lmbstudiocontact/mb5_1/raw/main/BossBabyCartoon_L5_156863955.bin",
    "id_bin": "BossBabyCartoon_L5_156863955",
    "list_language": [
      {
        "author": "LMB Studio",
        "link_thumb": "https://live.staticflickr.com/65535/51779343892_4144480f70_o.gif",
        "link_bin": "https://github.com/lmbstudiocontact/mb5_1/raw/main/BossBabyCartoon_L5_156863955_English.bin",
        "name_language": "English",
        "id_bin_language": "BossBabyCartoon_L5_156863955_English"
      },
      {
        "author": "LMB Studio",
        "link_thumb": "https://live.staticflickr.com/65535/51780160516_bdc708d320_o.gif",
        "link_bin": "https://github.com/lmbstudiocontact/mb5_1/raw/main/BossBabyCartoon_L5_156863955_Portuguese.bin",
        "name_language": "Portuguese",
        "id_bin_language": "BossBabyCartoon_L5_156863955_Portuguese"
      },
      {
        "author": "LMB Studio",
        "link_thumb": "https://live.staticflickr.com/65535/51779343782_6a94656acd_o.gif",
        "link_bin": "https://github.com/lmbstudiocontact/mb5_1/raw/main/BossBabyCartoon_L5_156863955_Russian.bin",
        "name_language": "Russian",
        "id_bin_language": "BossBabyCartoon_L5_156863955_Russian"
      },
      {
        "author": "LMB Studio",
        "link_thumb": "https://live.staticflickr.com/65535/51780409283_0f8cf46f18_o.gif",
        "link_bin": "https://github.com/lmbstudiocontact/mb5_1/raw/main/BossBabyCartoon_L5_156863955_Spanish.bin",
        "name_language": "Spanish",
        "id_bin_language": "BossBabyCartoon_L5_156863955_Spanish"
      }
    ],
    "array_tags": [
      "lmbstudio"
    ],
    "list_album": [
      {
        "id_album": "158762705",
        "link_thumb": "https://live.staticflickr.com/65535/51780409453_07dd147386_o.gif",
        "title": "Boss Baby Cartoon_L5"
      }
    ]
  },
  {
    "author": "Eliud",
    "link_thumb": "https://live.staticflickr.com/65535/51694770204_ceef2e9275_o.gif",
    "link_bin": "https://github.com/lmbstudiocontact/mb5_12/raw/main/1867.bin",
    "id_bin": "1867",
    "list_language": [],
    "array_tags": [
      "watchface",
      "miband5"
    ],
    "list_album": [
      {
        "id_album": "2433880",
        "link_thumb": "https://live.staticflickr.com/65535/51694770204_ceef2e9275_o.gif",
        "title": "None"
      }
    ]
  },
  {
    "author": "ilidio.martins",
    "link_thumb": "https://live.staticflickr.com/65535/51693304582_18fc0cfedb_o.gif",
    "link_bin": "https://github.com/lmbstudiocontact/mb5_12/raw/main/1893.bin",
    "id_bin": "1893",
    "list_language": [],
    "array_tags": [
      "digital",
      "distance",
      "heartrate",
      "weather",
      "battery",
      "steps"
    ],
    "list_album": [
      {
        "id_album": "2433880",
        "link_thumb": "https://live.staticflickr.com/65535/51693304582_18fc0cfedb_o.gif",
        "title": "None"
      }
    ]
  },
  {
    "author": "sgssantos",
    "link_thumb": "https://live.staticflickr.com/65535/51693288687_d33f1f3ef0_o.gif",
    "link_bin": "https://github.com/lmbstudiocontact/mb5_12/raw/main/1773.bin",
    "id_bin": "1773",
    "list_language": [],
    "array_tags": [
      "digital",
      "date",
      "heartrate",
      "weather",
      "battery",
      "steps"
    ],
    "list_album": [
      {
        "id_album": "2433880",
        "link_thumb": "https://live.staticflickr.com/65535/51693288687_d33f1f3ef0_o.gif",
        "title": "None"
      }
    ]
  },
  {
    "author": "shymik",
    "link_thumb": "https://live.staticflickr.com/65535/51694070056_1b387d1ea1_o.gif",
    "link_bin": "https://github.com/lmbstudiocontact/mb5_12/raw/main/1682.bin",
    "id_bin": "1682",
    "list_language": [],
    "array_tags": [
      "digital",
      "date",
      "floors",
      "distance",
      "heartrate",
      "weather",
      "calories",
      "battery",
      "steps"
    ],
    "list_album": [
      {
        "id_album": "2433880",
        "link_thumb": "https://live.staticflickr.com/65535/51694070056_1b387d1ea1_o.gif",
        "title": "None"
      }
    ]
  },
  {
    "author": "None",
    "link_thumb": "https://live.staticflickr.com/65535/51700058361_379e56f5fb_o.gif",
    "link_bin": "https://github.com/lmbstudiocontact/mb5_38/raw/main/M0047.bin",
    "id_bin": "M0047",
    "list_language": [],
    "array_tags": [],
    "list_album": [
      {
        "id_album": "-583089738",
        "link_thumb": "https://live.staticflickr.com/65535/51700058361_379e56f5fb_o.gif",
        "title": "Mifit Store"
      }
    ]
  },
  {
    "author": "LMB Studio",
    "link_thumb": "https://live.staticflickr.com/65535/51780801329_44dd88595f_o.gif",
    "link_bin": "https://github.com/lmbstudiocontact/mb5_1/raw/main/BossBabyCartoon_L5_446268251.bin",
    "id_bin": "BossBabyCartoon_L5_446268251",
    "list_language": [
      {
        "author": "LMB Studio",
        "link_thumb": "https://live.staticflickr.com/65535/51781043530_6720d4ce21_o.gif",
        "link_bin": "https://github.com/lmbstudiocontact/mb5_1/raw/main/BossBabyCartoon_L5_446268251_English.bin",
        "name_language": "English",
        "id_bin_language": "BossBabyCartoon_L5_446268251_English"
      },
      {
        "author": "LMB Studio",
        "link_thumb": "https://live.staticflickr.com/65535/51780160131_2487ce1b10_o.gif",
        "link_bin": "https://github.com/lmbstudiocontact/mb5_1/raw/main/BossBabyCartoon_L5_446268251_Portuguese.bin",
        "name_language": "Portuguese",
        "id_bin_language": "BossBabyCartoon_L5_446268251_Portuguese"
      },
      {
        "author": "LMB Studio",
        "link_thumb": "https://live.staticflickr.com/65535/51780160096_8505fee3b8_o.gif",
        "link_bin": "https://github.com/lmbstudiocontact/mb5_1/raw/main/BossBabyCartoon_L5_446268251_Russian.bin",
        "name_language": "Russian",
        "id_bin_language": "BossBabyCartoon_L5_446268251_Russian"
      },
      {
        "author": "LMB Studio",
        "link_thumb": "https://live.staticflickr.com/65535/51780160041_2e12e815d2_o.gif",
        "link_bin": "https://github.com/lmbstudiocontact/mb5_1/raw/main/BossBabyCartoon_L5_446268251_Spanish.bin",
        "name_language": "Spanish",
        "id_bin_language": "BossBabyCartoon_L5_446268251_Spanish"
      }
    ],
    "array_tags": [
      "lmbstudio"
    ],
    "list_album": [
      {
        "id_album": "158762705",
        "link_thumb": "https://live.staticflickr.com/65535/51780801329_44dd88595f_o.gif",
        "title": "Boss Baby Cartoon_L5"
      }
    ]
  },
  {
    "author": "LMB Studio",
    "link_thumb": "https://live.staticflickr.com/65535/51695078656_6e212334cf_o.gif",
    "link_bin": "https://github.com/lmbstudiocontact/mb5_3/raw/main/Boy_L6_-239647602.bin",
    "id_bin": "Boy_L6_-239647602",
    "list_language": [
      {
        "author": "LMB Studio",
        "link_thumb": "https://live.staticflickr.com/65535/51694287782_cf464e2ed1_o.gif",
        "link_bin": "https://github.com/lmbstudiocontact/mb5_3/raw/main/Boy_L6_-239647602_English.bin",
        "name_language": "English",
        "id_bin_language": "Boy_L6_-239647602_English"
      },
      {
        "author": "LMB Studio",
        "link_thumb": "https://live.staticflickr.com/65535/51694288147_259ae8b9ea_o.gif",
        "link_bin": "https://github.com/lmbstudiocontact/mb5_3/raw/main/Boy_L6_-239647602_Portuguese.bin",
        "name_language": "Portuguese",
        "id_bin_language": "Boy_L6_-239647602_Portuguese"
      },
      {
        "author": "LMB Studio",
        "link_thumb": "https://live.staticflickr.com/65535/51695760579_acf0eeac7f_o.gif",
        "link_bin": "https://github.com/lmbstudiocontact/mb5_3/raw/main/Boy_L6_-239647602_Russian.bin",
        "name_language": "Russian",
        "id_bin_language": "Boy_L6_-239647602_Russian"
      },
      {
        "author": "LMB Studio",
        "link_thumb": "https://live.staticflickr.com/65535/51695972565_1609c632c3_o.gif",
        "link_bin": "https://github.com/lmbstudiocontact/mb5_3/raw/main/Boy_L6_-239647602_Spanish.bin",
        "name_language": "Spanish",
        "id_bin_language": "Boy_L6_-239647602_Spanish"
      }
    ],
    "array_tags": [
      "lmbstudio"
    ],
    "list_album": [
      {
        "id_album": "1995733213",
        "link_thumb": "https://live.staticflickr.com/65535/51695078656_6e212334cf_o.gif",
        "title": "Boy_L6"
      }
    ]
  },
  {
    "author": "RuleDJ",
    "link_thumb": "https://live.staticflickr.com/65535/51694398498_a21001125a_o.gif",
    "link_bin": "https://github.com/lmbstudiocontact/mb5_12/raw/main/2121.bin",
    "id_bin": "2121",
    "list_language": [],
    "array_tags": [
      "digital",
      "date",
      "heartrate",
      "weather",
      "alarm",
      "humidity",
      "dnd",
      "battery"
    ],
    "list_album": [
      {
        "id_album": "2433880",
        "link_thumb": "https://live.staticflickr.com/65535/51694398498_a21001125a_o.gif",
        "title": "None"
      }
    ]
  },
  {
    "author": "LMB Studio",
    "link_thumb": "https://live.staticflickr.com/65535/51695151031_a4b8b725e8_o.gif",
    "link_bin": "https://github.com/lmbstudiocontact/mb5_3/raw/main/Boy_L6_537247521.bin",
    "id_bin": "Boy_L6_537247521",
    "list_language": [
      {
        "author": "LMB Studio",
        "link_thumb": "https://live.staticflickr.com/65535/51695832649_42d4f46754_o.gif",
        "link_bin": "https://github.com/lmbstudiocontact/mb5_3/raw/main/Boy_L6_537247521_English.bin",
        "name_language": "English",
        "id_bin_language": "Boy_L6_537247521_English"
      },
      {
        "author": "LMB Studio",
        "link_thumb": "https://live.staticflickr.com/65535/51694359827_8253991b7c_o.gif",
        "link_bin": "https://github.com/lmbstudiocontact/mb5_3/raw/main/Boy_L6_537247521_Portuguese.bin",
        "name_language": "Portuguese",
        "id_bin_language": "Boy_L6_537247521_Portuguese"
      },
      {
        "author": "LMB Studio",
        "link_thumb": "https://live.staticflickr.com/65535/51695833379_9e2c66274b_o.gif",
        "link_bin": "https://github.com/lmbstudiocontact/mb5_3/raw/main/Boy_L6_537247521_Russian.bin",
        "name_language": "Russian",
        "id_bin_language": "Boy_L6_537247521_Russian"
      },
      {
        "author": "LMB Studio",
        "link_thumb": "https://live.staticflickr.com/65535/51696044340_f33924411e_o.gif",
        "link_bin": "https://github.com/lmbstudiocontact/mb5_3/raw/main/Boy_L6_537247521_Spanish.bin",
        "name_language": "Spanish",
        "id_bin_language": "Boy_L6_537247521_Spanish"
      }
    ],
    "array_tags": [
      "lmbstudio"
    ],
    "list_album": [
      {
        "id_album": "1995733213",
        "link_thumb": "https://live.staticflickr.com/65535/51695151031_a4b8b725e8_o.gif",
        "title": "Boy_L6"
      }
    ]
  },
  {
    "author": "LMB Studio",
    "link_thumb": "https://live.staticflickr.com/65535/51694311687_6baa42292e_o.gif",
    "link_bin": "https://github.com/lmbstudiocontact/mb5_3/raw/main/Boy_L6_-944583198.bin",
    "id_bin": "Boy_L6_-944583198",
    "list_language": [
      {
        "author": "LMB Studio",
        "link_thumb": "https://live.staticflickr.com/65535/51694312172_d931b6f32b_o.gif",
        "link_bin": "https://github.com/lmbstudiocontact/mb5_3/raw/main/Boy_L6_-944583198_English.bin",
        "name_language": "English",
        "id_bin_language": "Boy_L6_-944583198_English"
      },
      {
        "author": "LMB Studio",
        "link_thumb": "https://live.staticflickr.com/65535/51694312632_8d62bb3142_o.gif",
        "link_bin": "https://github.com/lmbstudiocontact/mb5_3/raw/main/Boy_L6_-944583198_Portuguese.bin",
        "name_language": "Portuguese",
        "id_bin_language": "Boy_L6_-944583198_Portuguese"
      },
      {
        "author": "LMB Studio",
        "link_thumb": "https://live.staticflickr.com/65535/51695380868_2e078cf5ca_o.gif",
        "link_bin": "https://github.com/lmbstudiocontact/mb5_3/raw/main/Boy_L6_-944583198_Russian.bin",
        "name_language": "Russian",
        "id_bin_language": "Boy_L6_-944583198_Russian"
      },
      {
        "author": "LMB Studio",
        "link_thumb": "https://live.staticflickr.com/65535/51695785529_593c41feb1_o.gif",
        "link_bin": "https://github.com/lmbstudiocontact/mb5_3/raw/main/Boy_L6_-944583198_Spanish.bin",
        "name_language": "Spanish",
        "id_bin_language": "Boy_L6_-944583198_Spanish"
      }
    ],
    "array_tags": [
      "lmbstudio"
    ],
    "list_album": [
      {
        "id_album": "1995733213",
        "link_thumb": "https://live.staticflickr.com/65535/51694311687_6baa42292e_o.gif",
        "title": "Boy_L6"
      }
    ]
  },
  {
    "author": "None",
    "link_thumb": "https://live.staticflickr.com/65535/51700943130_623edc482b_o.gif",
    "link_bin": "https://github.com/lmbstudiocontact/mb5_38/raw/main/M0046.bin",
    "id_bin": "M0046",
    "list_language": [
      {
        "author": "None",
        "link_thumb": "https://live.staticflickr.com/65535/51700334923_1fe453bd8d_o.gif",
        "link_bin": "https://github.com/lmbstudiocontact/mb5_38/raw/main/M0046_English.bin",
        "name_language": "English",
        "id_bin_language": "M0046_English"
      },
      {
        "author": "None",
        "link_thumb": "https://live.staticflickr.com/65535/51700731634_e3eaecc26b_o.gif",
        "link_bin": "https://github.com/lmbstudiocontact/mb5_38/raw/main/M0046_Portuguese.bin",
        "name_language": "Portuguese",
        "id_bin_language": "M0046_Portuguese"
      },
      {
        "author": "None",
        "link_thumb": "https://live.staticflickr.com/65535/51700057716_9e36978a1b_o.gif",
        "link_bin": "https://github.com/lmbstudiocontact/mb5_38/raw/main/M0046_Russian.bin",
        "name_language": "Russian",
        "id_bin_language": "M0046_Russian"
      },
      {
        "author": "None",
        "link_thumb": "https://live.staticflickr.com/65535/51699260827_e089f80401_o.gif",
        "link_bin": "https://github.com/lmbstudiocontact/mb5_38/raw/main/M0046_Spanish.bin",
        "name_language": "Spanish",
        "id_bin_language": "M0046_Spanish"
      }
    ],
    "array_tags": [],
    "list_album": [
      {
        "id_album": "-583089738",
        "link_thumb": "https://live.staticflickr.com/65535/51700943130_623edc482b_o.gif",
        "title": "Mifit Store"
      }
    ]
  },
  {
    "author": "vivikuyo",
    "link_thumb": "https://live.staticflickr.com/65535/51694649154_1514ed1494_o.gif",
    "link_bin": "https://github.com/lmbstudiocontact/mb5_12/raw/main/1029.bin",
    "id_bin": "1029",
    "list_language": [],
    "array_tags": [
      "green"
    ],
    "list_album": [
      {
        "id_album": "2433880",
        "link_thumb": "https://live.staticflickr.com/65535/51694649154_1514ed1494_o.gif",
        "title": "None"
      }
    ]
  },
  {
    "author": "LMB Studio",
    "link_thumb": "https://live.staticflickr.com/65535/51694313552_a128bdab01_o.gif",
    "link_bin": "https://github.com/lmbstudiocontact/mb5_3/raw/main/Boy_L6_-988175456.bin",
    "id_bin": "Boy_L6_-988175456",
    "list_language": [
      {
        "author": "LMB Studio",
        "link_thumb": "https://live.staticflickr.com/65535/51695786344_7bf7710714_o.gif",
        "link_bin": "https://github.com/lmbstudiocontact/mb5_3/raw/main/Boy_L6_-988175456_English.bin",
        "name_language": "English",
        "id_bin_language": "Boy_L6_-988175456_English"
      },
      {
        "author": "LMB Studio",
        "link_thumb": "https://live.staticflickr.com/65535/51695382433_817bec96b2_o.gif",
        "link_bin": "https://github.com/lmbstudiocontact/mb5_3/raw/main/Boy_L6_-988175456_Portuguese.bin",
        "name_language": "Portuguese",
        "id_bin_language": "Boy_L6_-988175456_Portuguese"
      },
      {
        "author": "LMB Studio",
        "link_thumb": "https://live.staticflickr.com/65535/51695998395_3ab60d4295_o.gif",
        "link_bin": "https://github.com/lmbstudiocontact/mb5_3/raw/main/Boy_L6_-988175456_Russian.bin",
        "name_language": "Russian",
        "id_bin_language": "Boy_L6_-988175456_Russian"
      },
      {
        "author": "LMB Studio",
        "link_thumb": "https://live.staticflickr.com/65535/51694315247_3479d5bf78_o.gif",
        "link_bin": "https://github.com/lmbstudiocontact/mb5_3/raw/main/Boy_L6_-988175456_Spanish.bin",
        "name_language": "Spanish",
        "id_bin_language": "Boy_L6_-988175456_Spanish"
      }
    ],
    "array_tags": [
      "lmbstudio"
    ],
    "list_album": [
      {
        "id_album": "1995733213",
        "link_thumb": "https://live.staticflickr.com/65535/51694313552_a128bdab01_o.gif",
        "title": "Boy_L6"
      }
    ]
  },
  {
    "author": "FelixAndersen",
    "link_thumb": "https://live.staticflickr.com/65535/51695084449_0ce8f6b768_o.gif",
    "link_bin": "https://github.com/lmbstudiocontact/mb5_3/raw/main/809.bin",
    "id_bin": "809",
    "list_language": [],
    "array_tags": [
      "digital",
      "date",
      "distance",
      "weather",
      "calories",
      "battery",
      "steps"
    ],
    "list_album": [
      {
        "id_album": "2433880",
        "link_thumb": "https://live.staticflickr.com/65535/51695084449_0ce8f6b768_o.gif",
        "title": "None"
      }
    ]
  },
  {
    "author": "dondo",
    "link_thumb": "https://live.staticflickr.com/65535/51694354628_593b476f16_o.gif",
    "link_bin": "https://github.com/lmbstudiocontact/mb5_12/raw/main/1776.bin",
    "id_bin": "1776",
    "list_language": [],
    "array_tags": [
      "digital"
    ],
    "list_album": [
      {
        "id_album": "2433880",
        "link_thumb": "https://live.staticflickr.com/65535/51694354628_593b476f16_o.gif",
        "title": "None"
      }
    ]
  },
  {
    "author": "LMB Studio",
    "link_thumb": "https://live.staticflickr.com/65535/51695980560_0bbf0c78ec_o.gif",
    "link_bin": "https://github.com/lmbstudiocontact/mb5_3/raw/main/Boy_L6_-305626779.bin",
    "id_bin": "Boy_L6_-305626779",
    "list_language": [
      {
        "author": "LMB Studio",
        "link_thumb": "https://live.staticflickr.com/65535/51695088591_9953d787c6_o.gif",
        "link_bin": "https://github.com/lmbstudiocontact/mb5_3/raw/main/Boy_L6_-305626779_English.bin",
        "name_language": "English",
        "id_bin_language": "Boy_L6_-305626779_English"
      },
      {
        "author": "LMB Studio",
        "link_thumb": "https://live.staticflickr.com/65535/51695769669_c30272b4c6_o.gif",
        "link_bin": "https://github.com/lmbstudiocontact/mb5_3/raw/main/Boy_L6_-305626779_Portuguese.bin",
        "name_language": "Portuguese",
        "id_bin_language": "Boy_L6_-305626779_Portuguese"
      },
      {
        "author": "LMB Studio",
        "link_thumb": "https://live.staticflickr.com/65535/51695981620_caaca8439d_o.gif",
        "link_bin": "https://github.com/lmbstudiocontact/mb5_3/raw/main/Boy_L6_-305626779_Russian.bin",
        "name_language": "Russian",
        "id_bin_language": "Boy_L6_-305626779_Russian"
      },
      {
        "author": "LMB Studio",
        "link_thumb": "https://live.staticflickr.com/65535/51695982100_b8ddddf435_o.gif",
        "link_bin": "https://github.com/lmbstudiocontact/mb5_3/raw/main/Boy_L6_-305626779_Spanish.bin",
        "name_language": "Spanish",
        "id_bin_language": "Boy_L6_-305626779_Spanish"
      }
    ],
    "array_tags": [
      "lmbstudio"
    ],
    "list_album": [
      {
        "id_album": "1995733213",
        "link_thumb": "https://live.staticflickr.com/65535/51695980560_0bbf0c78ec_o.gif",
        "title": "Boy_L6"
      }
    ]
  },
  {
    "author": "LMB Studio",
    "link_thumb": "https://live.staticflickr.com/65535/51779342862_0ce165df44_o.gif",
    "link_bin": "https://github.com/lmbstudiocontact/mb5_1/raw/main/BossBabyCartoon_L5_1224678306.bin",
    "id_bin": "BossBabyCartoon_L5_1224678306",
    "list_language": [
      {
        "author": "LMB Studio",
        "link_thumb": "https://live.staticflickr.com/65535/51779342827_f72a791b32_o.gif",
        "link_bin": "https://github.com/lmbstudiocontact/mb5_1/raw/main/BossBabyCartoon_L5_1224678306_English.bin",
        "name_language": "English",
        "id_bin_language": "BossBabyCartoon_L5_1224678306_English"
      },
      {
        "author": "LMB Studio",
        "link_thumb": "https://live.staticflickr.com/65535/51781042910_4a3c836340_o.gif",
        "link_bin": "https://github.com/lmbstudiocontact/mb5_1/raw/main/BossBabyCartoon_L5_1224678306_Portuguese.bin",
        "name_language": "Portuguese",
        "id_bin_language": "BossBabyCartoon_L5_1224678306_Portuguese"
      },
      {
        "author": "LMB Studio",
        "link_thumb": "https://live.staticflickr.com/65535/51780800544_29e57692a9_o.gif",
        "link_bin": "https://github.com/lmbstudiocontact/mb5_1/raw/main/BossBabyCartoon_L5_1224678306_Russian.bin",
        "name_language": "Russian",
        "id_bin_language": "BossBabyCartoon_L5_1224678306_Russian"
      },
      {
        "author": "LMB Studio",
        "link_thumb": "https://live.staticflickr.com/65535/51781042815_944cd7c19b_o.gif",
        "link_bin": "https://github.com/lmbstudiocontact/mb5_1/raw/main/BossBabyCartoon_L5_1224678306_Spanish.bin",
        "name_language": "Spanish",
        "id_bin_language": "BossBabyCartoon_L5_1224678306_Spanish"
      }
    ],
    "array_tags": [
      "lmbstudio"
    ],
    "list_album": [
      {
        "id_album": "158762705",
        "link_thumb": "https://live.staticflickr.com/65535/51779342862_0ce165df44_o.gif",
        "title": "Boss Baby Cartoon_L5"
      }
    ]
  },
  {
    "author": "LMB Studio",
    "link_thumb": "https://live.staticflickr.com/65535/51780801109_51d4991428_o.gif",
    "link_bin": "https://github.com/lmbstudiocontact/mb5_1/raw/main/BossBabyCartoon_L5_1196419382.bin",
    "id_bin": "BossBabyCartoon_L5_1196419382",
    "list_language": [
      {
        "author": "LMB Studio",
        "link_thumb": "https://live.staticflickr.com/65535/51780408923_3233422d50_o.gif",
        "link_bin": "https://github.com/lmbstudiocontact/mb5_1/raw/main/BossBabyCartoon_L5_1196419382_English.bin",
        "name_language": "English",
        "id_bin_language": "BossBabyCartoon_L5_1196419382_English"
      },
      {
        "author": "LMB Studio",
        "link_thumb": "https://live.staticflickr.com/65535/51781043310_af5a6697d5_o.gif",
        "link_bin": "https://github.com/lmbstudiocontact/mb5_1/raw/main/BossBabyCartoon_L5_1196419382_Portuguese.bin",
        "name_language": "Portuguese",
        "id_bin_language": "BossBabyCartoon_L5_1196419382_Portuguese"
      },
      {
        "author": "LMB Studio",
        "link_thumb": "https://live.staticflickr.com/65535/51780159886_17ba292eec_o.gif",
        "link_bin": "https://github.com/lmbstudiocontact/mb5_1/raw/main/BossBabyCartoon_L5_1196419382_Russian.bin",
        "name_language": "Russian",
        "id_bin_language": "BossBabyCartoon_L5_1196419382_Russian"
      },
      {
        "author": "LMB Studio",
        "link_thumb": "https://live.staticflickr.com/65535/51781043245_ab2d61494a_o.gif",
        "link_bin": "https://github.com/lmbstudiocontact/mb5_1/raw/main/BossBabyCartoon_L5_1196419382_Spanish.bin",
        "name_language": "Spanish",
        "id_bin_language": "BossBabyCartoon_L5_1196419382_Spanish"
      }
    ],
    "array_tags": [
      "lmbstudio"
    ],
    "list_album": [
      {
        "id_album": "158762705",
        "link_thumb": "https://live.staticflickr.com/65535/51780801109_51d4991428_o.gif",
        "title": "Boss Baby Cartoon_L5"
      }
    ]
  },
  {
    "author": "Lamachin",
    "link_thumb": "https://live.staticflickr.com/65535/51694411233_6bb512d115_o.gif",
    "link_bin": "https://github.com/lmbstudiocontact/mb5_0/raw/main/224.bin",
    "id_bin": "224",
    "list_language": [],
    "array_tags": [
      "digital",
      "date",
      "distance",
      "heartrate",
      "alarm",
      "battery",
      "steps"
    ],
    "list_album": [
      {
        "id_album": "2433880",
        "link_thumb": "https://live.staticflickr.com/65535/51694411233_6bb512d115_o.gif",
        "title": "None"
      }
    ]
  },
  {
    "author": "vuong205",
    "link_thumb": "https://live.staticflickr.com/65535/51694671119_7851c9d422_o.gif",
    "link_bin": "https://github.com/lmbstudiocontact/mb5_12/raw/main/1199.bin",
    "id_bin": "1199",
    "list_language": [],
    "array_tags": [
      "digital",
      "date",
      "heartrate",
      "weather",
      "battery",
      "steps"
    ],
    "list_album": [
      {
        "id_album": "2433880",
        "link_thumb": "https://live.staticflickr.com/65535/51694671119_7851c9d422_o.gif",
        "title": "None"
      }
    ]
  },
  {
    "author": "zsoltee69",
    "link_thumb": "https://live.staticflickr.com/65535/51694994255_5695899d5b_o.gif",
    "link_bin": "https://github.com/lmbstudiocontact/mb5_12/raw/main/1947.bin",
    "id_bin": "1947",
    "list_language": [],
    "array_tags": [
      "date",
      "digital",
      "analog",
      "distance",
      "heartrate",
      "weather",
      "battery",
      "steps"
    ],
    "list_album": [
      {
        "id_album": "2433880",
        "link_thumb": "https://live.staticflickr.com/65535/51694994255_5695899d5b_o.gif",
        "title": "None"
      }
    ]
  },
  {
    "author": "LMB Studio",
    "link_thumb": "https://live.staticflickr.com/65535/51695666358_784a0c48e2_o.gif",
    "link_bin": "https://github.com/lmbstudiocontact/mb5_27/raw/main/Cat_L6_-525203852.bin",
    "id_bin": "Cat_L6_-525203852",
    "list_language": [
      {
        "author": "LMB Studio",
        "link_thumb": "https://live.staticflickr.com/65535/51696281780_0ddf767d41_o.gif",
        "link_bin": "https://github.com/lmbstudiocontact/mb5_27/raw/main/Cat_L6_-525203852_English.bin",
        "name_language": "English",
        "id_bin_language": "Cat_L6_-525203852_English"
      },
      {
        "author": "LMB Studio",
        "link_thumb": "https://live.staticflickr.com/65535/51696069944_178aea1d80_o.gif",
        "link_bin": "https://github.com/lmbstudiocontact/mb5_27/raw/main/Cat_L6_-525203852_Portuguese.bin",
        "name_language": "Portuguese",
        "id_bin_language": "Cat_L6_-525203852_Portuguese"
      },
      {
        "author": "LMB Studio",
        "link_thumb": "https://live.staticflickr.com/65535/51695389126_6017b69938_o.gif",
        "link_bin": "https://github.com/lmbstudiocontact/mb5_27/raw/main/Cat_L6_-525203852_Russian.bin",
        "name_language": "Russian",
        "id_bin_language": "Cat_L6_-525203852_Russian"
      },
      {
        "author": "LMB Studio",
        "link_thumb": "https://live.staticflickr.com/65535/51695389446_7f4882d92e_o.gif",
        "link_bin": "https://github.com/lmbstudiocontact/mb5_27/raw/main/Cat_L6_-525203852_Spanish.bin",
        "name_language": "Spanish",
        "id_bin_language": "Cat_L6_-525203852_Spanish"
      }
    ],
    "array_tags": [
      "lmbstudio"
    ],
    "list_album": [
      {
        "id_album": "2011284115",
        "link_thumb": "https://live.staticflickr.com/65535/51695666358_784a0c48e2_o.gif",
        "title": "Cat_L6"
      }
    ]
  },
  {
    "author": "LMB Studio",
    "link_thumb": "https://live.staticflickr.com/65535/51695781824_9087e34b43_o.gif",
    "link_bin": "https://github.com/lmbstudiocontact/mb5_3/raw/main/Boy_L6_-944583170.bin",
    "id_bin": "Boy_L6_-944583170",
    "list_language": [
      {
        "author": "LMB Studio",
        "link_thumb": "https://live.staticflickr.com/65535/51695377943_b9f1bfd91d_o.gif",
        "link_bin": "https://github.com/lmbstudiocontact/mb5_3/raw/main/Boy_L6_-944583170_English.bin",
        "name_language": "English",
        "id_bin_language": "Boy_L6_-944583170_English"
      },
      {
        "author": "LMB Studio",
        "link_thumb": "https://live.staticflickr.com/65535/51695102161_492a2d59ff_o.gif",
        "link_bin": "https://github.com/lmbstudiocontact/mb5_3/raw/main/Boy_L6_-944583170_Portuguese.bin",
        "name_language": "Portuguese",
        "id_bin_language": "Boy_L6_-944583170_Portuguese"
      },
      {
        "author": "LMB Studio",
        "link_thumb": "https://live.staticflickr.com/65535/51694310847_8d91cc39ec_o.gif",
        "link_bin": "https://github.com/lmbstudiocontact/mb5_3/raw/main/Boy_L6_-944583170_Russian.bin",
        "name_language": "Russian",
        "id_bin_language": "Boy_L6_-944583170_Russian"
      },
      {
        "author": "LMB Studio",
        "link_thumb": "https://live.staticflickr.com/65535/51694311277_b32c0a1822_o.gif",
        "link_bin": "https://github.com/lmbstudiocontact/mb5_3/raw/main/Boy_L6_-944583170_Spanish.bin",
        "name_language": "Spanish",
        "id_bin_language": "Boy_L6_-944583170_Spanish"
      }
    ],
    "array_tags": [
      "lmbstudio"
    ],
    "list_album": [
      {
        "id_album": "1995733213",
        "link_thumb": "https://live.staticflickr.com/65535/51695781824_9087e34b43_o.gif",
        "title": "Boy_L6"
      }
    ]
  },
  {
    "author": "becamer",
    "link_thumb": "https://live.staticflickr.com/65535/51694429336_0ddeeb1380_o.gif",
    "link_bin": "https://github.com/lmbstudiocontact/mb5_3/raw/main/92.bin",
    "id_bin": "92",
    "list_language": [],
    "array_tags": [
      "game",
      "green",
      "gta"
    ],
    "list_album": [
      {
        "id_album": "2231123",
        "link_thumb": "https://live.staticflickr.com/65535/51694429336_0ddeeb1380_o.gif",
        "title": "Guns"
      }
    ]
  },
  {
    "author": "None",
    "link_thumb": "https://live.staticflickr.com/65535/51700336683_9e277df715_o.gif",
    "link_bin": "https://github.com/lmbstudiocontact/mb5_38/raw/main/M0048.bin",
    "id_bin": "M0048",
    "list_language": [
      {
        "author": "None",
        "link_thumb": "https://live.staticflickr.com/65535/51700337278_2808f1965e_o.gif",
        "link_bin": "https://github.com/lmbstudiocontact/mb5_38/raw/main/M0048_English.bin",
        "name_language": "English",
        "id_bin_language": "M0048_English"
      },
      {
        "author": "None",
        "link_thumb": "https://live.staticflickr.com/65535/51700059501_3f8b65390d_o.gif",
        "link_bin": "https://github.com/lmbstudiocontact/mb5_38/raw/main/M0048_Portuguese.bin",
        "name_language": "Portuguese",
        "id_bin_language": "M0048_Portuguese"
      },
      {
        "author": "None",
        "link_thumb": "https://live.staticflickr.com/65535/51700059781_5a28587da6_o.gif",
        "link_bin": "https://github.com/lmbstudiocontact/mb5_38/raw/main/M0048_Russian.bin",
        "name_language": "Russian",
        "id_bin_language": "M0048_Russian"
      },
      {
        "author": "None",
        "link_thumb": "https://live.staticflickr.com/65535/51700060351_7f9bd5922e_o.gif",
        "link_bin": "https://github.com/lmbstudiocontact/mb5_38/raw/main/M0048_Spanish.bin",
        "name_language": "Spanish",
        "id_bin_language": "M0048_Spanish"
      }
    ],
    "array_tags": [],
    "list_album": [
      {
        "id_album": "-583089738",
        "link_thumb": "https://live.staticflickr.com/65535/51700336683_9e277df715_o.gif",
        "title": "Mifit Store"
      }
    ]
  },
  {
    "author": "None",
    "link_thumb": "https://live.staticflickr.com/65535/51700056226_61ee9c6bd6_o.gif",
    "link_bin": "https://github.com/lmbstudiocontact/mb5_38/raw/main/M0045.bin",
    "id_bin": "M0045",
    "list_language": [],
    "array_tags": [],
    "list_album": [
      {
        "id_album": "-583089738",
        "link_thumb": "https://live.staticflickr.com/65535/51700056226_61ee9c6bd6_o.gif",
        "title": "Mifit Store"
      }
    ]
  },
  {
    "author": "Mirbo",
    "link_thumb": "https://live.staticflickr.com/65535/51694444246_549f3d7e8e_o.gif",
    "link_bin": "https://github.com/lmbstudiocontact/mb5_23/raw/main/980.bin",
    "id_bin": "980",
    "list_language": [],
    "array_tags": [
      "date",
      "weekday",
      "time",
      "battery",
      "steps"
    ],
    "list_album": [
      {
        "id_album": "2433880",
        "link_thumb": "https://live.staticflickr.com/65535/51694444246_549f3d7e8e_o.gif",
        "title": "None"
      }
    ]
  },
  {
    "author": "nekofirefox_AR",
    "link_thumb": "https://live.staticflickr.com/65535/51694247748_7ff4b9e05e_o.gif",
    "link_bin": "https://github.com/lmbstudiocontact/mb5_12/raw/main/1038.bin",
    "id_bin": "1038",
    "list_language": [],
    "array_tags": [
      "digital",
      "heartrate"
    ],
    "list_album": [
      {
        "id_album": "2433880",
        "link_thumb": "https://live.staticflickr.com/65535/51694247748_7ff4b9e05e_o.gif",
        "title": "None"
      }
    ]
  },
  {
    "author": "Eliud",
    "link_thumb": "https://live.staticflickr.com/65535/51693312722_4d2b683bb6_o.gif",
    "link_bin": "https://github.com/lmbstudiocontact/mb5_12/raw/main/1949.bin",
    "id_bin": "1949",
    "list_language": [],
    "array_tags": [
      "watchface",
      "miband5"
    ],
    "list_album": [
      {
        "id_album": "2433880",
        "link_thumb": "https://live.staticflickr.com/65535/51693312722_4d2b683bb6_o.gif",
        "title": "None"
      }
    ]
  },
  {
    "author": "themoneyfactory",
    "link_thumb": "https://live.staticflickr.com/65535/51694360366_7cc21fd309_o.gif",
    "link_bin": "https://github.com/lmbstudiocontact/mb5_3/raw/main/585.bin",
    "id_bin": "585",
    "list_language": [],
    "array_tags": [
      "digital",
      "date",
      "seconds",
      "battery"
    ],
    "list_album": [
      {
        "id_album": "2433880",
        "link_thumb": "https://live.staticflickr.com/65535/51694360366_7cc21fd309_o.gif",
        "title": "None"
      }
    ]
  },
  {
    "author": "Ben.Hoang",
    "link_thumb": "https://live.staticflickr.com/65535/51695078820_c08ac1445d_o.gif",
    "link_bin": "https://github.com/lmbstudiocontact/mb5_0/raw/main/28.bin",
    "id_bin": "28",
    "list_language": [],
    "array_tags": [
      "battery",
      "steps"
    ],
    "list_album": [
      {
        "id_album": "63410260",
        "link_thumb": "https://live.staticflickr.com/65535/51695078820_c08ac1445d_o.gif",
        "title": "Anime"
      }
    ]
  },
  {
    "author": "ahidzatx",
    "link_thumb": "https://live.staticflickr.com/65535/51694687633_a932290628_o.gif",
    "link_bin": "https://github.com/lmbstudiocontact/mb5_3/raw/main/843.bin",
    "id_bin": "843",
    "list_language": [],
    "array_tags": [
      "digital",
      "date",
      "distance",
      "heartrate",
      "weather",
      "calories",
      "battery",
      "steps"
    ],
    "list_album": [
      {
        "id_album": "2433880",
        "link_thumb": "https://live.staticflickr.com/65535/51694687633_a932290628_o.gif",
        "title": "None"
      }
    ]
  },
  {
    "author": "None",
    "link_thumb": "https://live.staticflickr.com/65535/51699268307_6cf34bdcfb_o.gif",
    "link_bin": "https://github.com/lmbstudiocontact/mb5_38/raw/main/M0052.bin",
    "id_bin": "M0052",
    "list_language": [
      {
        "author": "None",
        "link_thumb": "https://live.staticflickr.com/65535/51700952685_1df483c20a_o.gif",
        "link_bin": "https://github.com/lmbstudiocontact/mb5_38/raw/main/M0052_English.bin",
        "name_language": "English",
        "id_bin_language": "M0052_English"
      },
      {
        "author": "None",
        "link_thumb": "https://live.staticflickr.com/65535/51700740664_08981306a3_o.gif",
        "link_bin": "https://github.com/lmbstudiocontact/mb5_38/raw/main/M0052_Portuguese.bin",
        "name_language": "Portuguese",
        "id_bin_language": "M0052_Portuguese"
      },
      {
        "author": "None",
        "link_thumb": "https://live.staticflickr.com/65535/51700066651_ea6ab8ac46_o.gif",
        "link_bin": "https://github.com/lmbstudiocontact/mb5_38/raw/main/M0052_Russian.bin",
        "name_language": "Russian",
        "id_bin_language": "M0052_Russian"
      },
      {
        "author": "None",
        "link_thumb": "https://live.staticflickr.com/65535/51699269552_8591c7a877_o.gif",
        "link_bin": "https://github.com/lmbstudiocontact/mb5_38/raw/main/M0052_Spanish.bin",
        "name_language": "Spanish",
        "id_bin_language": "M0052_Spanish"
      }
    ],
    "array_tags": [],
    "list_album": [
      {
        "id_album": "-583089738",
        "link_thumb": "https://live.staticflickr.com/65535/51699268307_6cf34bdcfb_o.gif",
        "title": "Mifit Store"
      }
    ]
  },
  {
    "author": "LMB Studio",
    "link_thumb": "https://live.staticflickr.com/65535/51694289502_fef1ff46c0_o.gif",
    "link_bin": "https://github.com/lmbstudiocontact/mb5_3/raw/main/Boy_L6_-239647665.bin",
    "id_bin": "Boy_L6_-239647665",
    "list_language": [
      {
        "author": "LMB Studio",
        "link_thumb": "https://live.staticflickr.com/65535/51695357173_7ae38205d1_o.gif",
        "link_bin": "https://github.com/lmbstudiocontact/mb5_3/raw/main/Boy_L6_-239647665_English.bin",
        "name_language": "English",
        "id_bin_language": "Boy_L6_-239647665_English"
      },
      {
        "author": "LMB Studio",
        "link_thumb": "https://live.staticflickr.com/65535/51695974020_b4d4ec4066_o.gif",
        "link_bin": "https://github.com/lmbstudiocontact/mb5_3/raw/main/Boy_L6_-239647665_Portuguese.bin",
        "name_language": "Portuguese",
        "id_bin_language": "Boy_L6_-239647665_Portuguese"
      },
      {
        "author": "LMB Studio",
        "link_thumb": "https://live.staticflickr.com/65535/51695358248_0eb6693c71_o.gif",
        "link_bin": "https://github.com/lmbstudiocontact/mb5_3/raw/main/Boy_L6_-239647665_Russian.bin",
        "name_language": "Russian",
        "id_bin_language": "Boy_L6_-239647665_Russian"
      },
      {
        "author": "LMB Studio",
        "link_thumb": "https://live.staticflickr.com/65535/51695082636_329290ee0a_o.gif",
        "link_bin": "https://github.com/lmbstudiocontact/mb5_3/raw/main/Boy_L6_-239647665_Spanish.bin",
        "name_language": "Spanish",
        "id_bin_language": "Boy_L6_-239647665_Spanish"
      }
    ],
    "array_tags": [
      "lmbstudio"
    ],
    "list_album": [
      {
        "id_album": "1995733213",
        "link_thumb": "https://live.staticflickr.com/65535/51694289502_fef1ff46c0_o.gif",
        "title": "Boy_L6"
      }
    ]
  },
  {
    "author": "LMB Studio",
    "link_thumb": "https://live.staticflickr.com/65535/51695375248_1d5bd6ffb8_o.gif",
    "link_bin": "https://github.com/lmbstudiocontact/mb5_3/raw/main/Boy_L6_-944582454.bin",
    "id_bin": "Boy_L6_-944582454",
    "list_language": [
      {
        "author": "LMB Studio",
        "link_thumb": "https://live.staticflickr.com/65535/51695099406_f285e04164_o.gif",
        "link_bin": "https://github.com/lmbstudiocontact/mb5_3/raw/main/Boy_L6_-944582454_English.bin",
        "name_language": "English",
        "id_bin_language": "Boy_L6_-944582454_English"
      },
      {
        "author": "LMB Studio",
        "link_thumb": "https://live.staticflickr.com/65535/51695780449_6605a64943_o.gif",
        "link_bin": "https://github.com/lmbstudiocontact/mb5_3/raw/main/Boy_L6_-944582454_Portuguese.bin",
        "name_language": "Portuguese",
        "id_bin_language": "Boy_L6_-944582454_Portuguese"
      },
      {
        "author": "LMB Studio",
        "link_thumb": "https://live.staticflickr.com/65535/51695100276_b55b399a8f_o.gif",
        "link_bin": "https://github.com/lmbstudiocontact/mb5_3/raw/main/Boy_L6_-944582454_Russian.bin",
        "name_language": "Russian",
        "id_bin_language": "Boy_L6_-944582454_Russian"
      },
      {
        "author": "LMB Studio",
        "link_thumb": "https://live.staticflickr.com/65535/51695992765_24d08f8b9f_o.gif",
        "link_bin": "https://github.com/lmbstudiocontact/mb5_3/raw/main/Boy_L6_-944582454_Spanish.bin",
        "name_language": "Spanish",
        "id_bin_language": "Boy_L6_-944582454_Spanish"
      }
    ],
    "array_tags": [
      "lmbstudio"
    ],
    "list_album": [
      {
        "id_album": "1995733213",
        "link_thumb": "https://live.staticflickr.com/65535/51695375248_1d5bd6ffb8_o.gif",
        "title": "Boy_L6"
      }
    ]
  },
  {
    "author": "Dailson f.c",
    "link_thumb": "https://live.staticflickr.com/65535/51694681284_eb790b22e3_o.gif",
    "link_bin": "https://github.com/lmbstudiocontact/mb5_12/raw/main/1269.bin",
    "id_bin": "1269",
    "list_language": [],
    "array_tags": [
      "digital",
      "date",
      "distance",
      "heartrate",
      "weather",
      "calories",
      "battery",
      "steps"
    ],
    "list_album": [
      {
        "id_album": "2433880",
        "link_thumb": "https://live.staticflickr.com/65535/51694681284_eb790b22e3_o.gif",
        "title": "None"
      }
    ]
  },
  {
    "author": "RikardoTranzilo",
    "link_thumb": "https://live.staticflickr.com/65535/51693371262_ae72af86d3_o.gif",
    "link_bin": "https://github.com/lmbstudiocontact/mb5_22/raw/main/2568.bin",
    "id_bin": "2568",
    "list_language": [],
    "array_tags": [
      "naruto",
      "digital",
      "brasil",
      "portugues"
    ],
    "list_album": [
      {
        "id_album": "63410260",
        "link_thumb": "https://live.staticflickr.com/65535/51693371262_ae72af86d3_o.gif",
        "title": "Anime"
      }
    ]
  },
  {
    "author": "awrun",
    "link_thumb": "https://live.staticflickr.com/65535/51694853699_476a61e444_o.gif",
    "link_bin": "https://github.com/lmbstudiocontact/mb5_0/raw/main/268.bin",
    "id_bin": "268",
    "list_language": [],
    "array_tags": [
      "digital",
      "date",
      "heartrate",
      "weather",
      "humidity",
      "battery",
      "steps",
      "wind"
    ],
    "list_album": [
      {
        "id_album": "2433880",
        "link_thumb": "https://live.staticflickr.com/65535/51694853699_476a61e444_o.gif",
        "title": "None"
      }
    ]
  },
  {
    "author": "LMB Studio",
    "link_thumb": "https://live.staticflickr.com/65535/51780160356_128b799542_o.gif",
    "link_bin": "https://github.com/lmbstudiocontact/mb5_1/raw/main/BossBabyCartoon_L5_157735423.bin",
    "id_bin": "BossBabyCartoon_L5_157735423",
    "list_language": [
      {
        "author": "LMB Studio",
        "link_thumb": "https://live.staticflickr.com/65535/51780409238_238f3a2b07_o.gif",
        "link_bin": "https://github.com/lmbstudiocontact/mb5_1/raw/main/BossBabyCartoon_L5_157735423_English.bin",
        "name_language": "English",
        "id_bin_language": "BossBabyCartoon_L5_157735423_English"
      },
      {
        "author": "LMB Studio",
        "link_thumb": "https://live.staticflickr.com/65535/51781043720_b734326a5d_o.gif",
        "link_bin": "https://github.com/lmbstudiocontact/mb5_1/raw/main/BossBabyCartoon_L5_157735423_Portuguese.bin",
        "name_language": "Portuguese",
        "id_bin_language": "BossBabyCartoon_L5_157735423_Portuguese"
      },
      {
        "author": "LMB Studio",
        "link_thumb": "https://live.staticflickr.com/65535/51779343567_e2bbdd7ab1_o.gif",
        "link_bin": "https://github.com/lmbstudiocontact/mb5_1/raw/main/BossBabyCartoon_L5_157735423_Russian.bin",
        "name_language": "Russian",
        "id_bin_language": "BossBabyCartoon_L5_157735423_Russian"
      },
      {
        "author": "LMB Studio",
        "link_thumb": "https://live.staticflickr.com/65535/51780409163_6775a1c618_o.gif",
        "link_bin": "https://github.com/lmbstudiocontact/mb5_1/raw/main/BossBabyCartoon_L5_157735423_Spanish.bin",
        "name_language": "Spanish",
        "id_bin_language": "BossBabyCartoon_L5_157735423_Spanish"
      }
    ],
    "array_tags": [
      "lmbstudio"
    ],
    "list_album": [
      {
        "id_album": "158762705",
        "link_thumb": "https://live.staticflickr.com/65535/51780160356_128b799542_o.gif",
        "title": "Boss Baby Cartoon_L5"
      }
    ]
  },
  {
    "author": "Soul89reg",
    "link_thumb": "https://live.staticflickr.com/65535/51695014900_f2b9d909cd_o.gif",
    "link_bin": "https://github.com/lmbstudiocontact/mb5_12/raw/main/2124.bin",
    "id_bin": "2124",
    "list_language": [],
    "array_tags": [
      "digital",
      "date",
      "seconds",
      "distance",
      "heartrate",
      "calories",
      "battery",
      "steps"
    ],
    "list_album": [
      {
        "id_album": "2433880",
        "link_thumb": "https://live.staticflickr.com/65535/51695014900_f2b9d909cd_o.gif",
        "title": "None"
      }
    ]
  },
  {
    "author": "NIXIAH",
    "link_thumb": "https://live.staticflickr.com/65535/51694421778_7bb4a114ee_o.gif",
    "link_bin": "https://github.com/lmbstudiocontact/mb5_0/raw/main/239.bin",
    "id_bin": "239",
    "list_language": [],
    "array_tags": [
      "digital",
      "date",
      "heartrate",
      "battery",
      "steps"
    ],
    "list_album": [
      {
        "id_album": "2433880",
        "link_thumb": "https://live.staticflickr.com/65535/51694421778_7bb4a114ee_o.gif",
        "title": "None"
      }
    ]
  },
  {
    "author": "donjohrian",
    "link_thumb": "https://live.staticflickr.com/65535/51693653727_1c2eaaed2e_o.gif",
    "link_bin": "https://github.com/lmbstudiocontact/mb5_23/raw/main/998.bin",
    "id_bin": "998",
    "list_language": [],
    "array_tags": [
      "date",
      "analog",
      "minimal",
      "time"
    ],
    "list_album": [
      {
        "id_album": "2433880",
        "link_thumb": "https://live.staticflickr.com/65535/51693653727_1c2eaaed2e_o.gif",
        "title": "None"
      }
    ]
  },
  {
    "author": "BuddhaBMF",
    "link_thumb": "https://live.staticflickr.com/65535/51694372303_ddf39fb58b_o.gif",
    "link_bin": "https://github.com/lmbstudiocontact/mb5_0/raw/main/190.bin",
    "id_bin": "190",
    "list_language": [],
    "array_tags": [],
    "list_album": [
      {
        "id_album": "2433880",
        "link_thumb": "https://live.staticflickr.com/65535/51694372303_ddf39fb58b_o.gif",
        "title": "None"
      }
    ]
  },
  {
    "author": "LMB Studio",
    "link_thumb": "https://live.staticflickr.com/65535/51694594312_9c4124e938_o.gif",
    "link_bin": "https://github.com/lmbstudiocontact/mb5_27/raw/main/Cat_L6_-525203795.bin",
    "id_bin": "Cat_L6_-525203795",
    "list_language": [
      {
        "author": "LMB Studio",
        "link_thumb": "https://live.staticflickr.com/65535/51696279700_9c14a2a253_o.gif",
        "link_bin": "https://github.com/lmbstudiocontact/mb5_27/raw/main/Cat_L6_-525203795_English.bin",
        "name_language": "English",
        "id_bin_language": "Cat_L6_-525203795_English"
      },
      {
        "author": "LMB Studio",
        "link_thumb": "https://live.staticflickr.com/65535/51695386671_ae5c09266f_o.gif",
        "link_bin": "https://github.com/lmbstudiocontact/mb5_27/raw/main/Cat_L6_-525203795_Portuguese.bin",
        "name_language": "Portuguese",
        "id_bin_language": "Cat_L6_-525203795_Portuguese"
      },
      {
        "author": "LMB Studio",
        "link_thumb": "https://live.staticflickr.com/65535/51694595892_0dbe2994ea_o.gif",
        "link_bin": "https://github.com/lmbstudiocontact/mb5_27/raw/main/Cat_L6_-525203795_Russian.bin",
        "name_language": "Russian",
        "id_bin_language": "Cat_L6_-525203795_Russian"
      },
      {
        "author": "LMB Studio",
        "link_thumb": "https://live.staticflickr.com/65535/51695665833_5a74f8dbca_o.gif",
        "link_bin": "https://github.com/lmbstudiocontact/mb5_27/raw/main/Cat_L6_-525203795_Spanish.bin",
        "name_language": "Spanish",
        "id_bin_language": "Cat_L6_-525203795_Spanish"
      }
    ],
    "array_tags": [
      "lmbstudio"
    ],
    "list_album": [
      {
        "id_album": "2011284115",
        "link_thumb": "https://live.staticflickr.com/65535/51694594312_9c4124e938_o.gif",
        "title": "Cat_L6"
      }
    ]
  },
  {
    "author": "None",
    "link_thumb": "https://live.staticflickr.com/65535/51695127485_5aa843f173_o.gif",
    "link_bin": "https://github.com/lmbstudiocontact/mb5_0/raw/main/31_fix.bin",
    "id_bin": "31_fix",
    "list_language": [],
    "array_tags": [],
    "list_album": [
      {
        "id_album": "63410260",
        "link_thumb": "https://live.staticflickr.com/65535/51695127485_5aa843f173_o.gif",
        "title": "Anime"
      }
    ]
  },
  {
    "author": "becamer",
    "link_thumb": "https://live.staticflickr.com/65535/51695102569_15b6cacab4_o.gif",
    "link_bin": "https://github.com/lmbstudiocontact/mb5_3/raw/main/90.bin",
    "id_bin": "90",
    "list_language": [],
    "array_tags": [
      "game",
      "gta"
    ],
    "list_album": [
      {
        "id_album": "2231123",
        "link_thumb": "https://live.staticflickr.com/65535/51695102569_15b6cacab4_o.gif",
        "title": "Guns"
      }
    ]
  },
  {
    "author": "ahidzatx",
    "link_thumb": "https://live.staticflickr.com/65535/51693620862_0309b2e9de_o.gif",
    "link_bin": "https://github.com/lmbstudiocontact/mb5_3/raw/main/844.bin",
    "id_bin": "844",
    "list_language": [],
    "array_tags": [
      "digital",
      "date",
      "seconds",
      "distance",
      "heartrate",
      "weather",
      "calories",
      "battery",
      "steps"
    ],
    "list_album": [
      {
        "id_album": "2433880",
        "link_thumb": "https://live.staticflickr.com/65535/51693620862_0309b2e9de_o.gif",
        "title": "None"
      }
    ]
  }
]