[
  {
    "author": "Lamachin",
    "link_thumb": "https://live.staticflickr.com/65535/51694411233_6bb512d115_o.gif",
    "link_bin": "https://github.com/lmbstudiocontact/mb5_0/raw/main/224.bin",
    "id_bin": "224",
    "list_language": [],
    "array_tags": [
      "digital",
      "date",
      "distance",
      "heartrate",
      "alarm",
      "battery",
      "steps"
    ],
    "list_album": [
      {
        "id_album": "2433880",
        "link_thumb": "https://live.staticflickr.com/65535/51694411233_6bb512d115_o.gif",
        "title": "None"
      }
    ]
  },
  {
    "author": "LMB Studio",
    "link_thumb": "https://live.staticflickr.com/65535/51780801109_51d4991428_o.gif",
    "link_bin": "https://github.com/lmbstudiocontact/mb5_1/raw/main/BossBabyCartoon_L5_1196419382.bin",
    "id_bin": "BossBabyCartoon_L5_1196419382",
    "list_language": [
      {
        "author": "LMB Studio",
        "link_thumb": "https://live.staticflickr.com/65535/51780408923_3233422d50_o.gif",
        "link_bin": "https://github.com/lmbstudiocontact/mb5_1/raw/main/BossBabyCartoon_L5_1196419382_English.bin",
        "name_language": "English",
        "id_bin_language": "BossBabyCartoon_L5_1196419382_English"
      },
      {
        "author": "LMB Studio",
        "link_thumb": "https://live.staticflickr.com/65535/51781043310_af5a6697d5_o.gif",
        "link_bin": "https://github.com/lmbstudiocontact/mb5_1/raw/main/BossBabyCartoon_L5_1196419382_Portuguese.bin",
        "name_language": "Portuguese",
        "id_bin_language": "BossBabyCartoon_L5_1196419382_Portuguese"
      },
      {
        "author": "LMB Studio",
        "link_thumb": "https://live.staticflickr.com/65535/51780159886_17ba292eec_o.gif",
        "link_bin": "https://github.com/lmbstudiocontact/mb5_1/raw/main/BossBabyCartoon_L5_1196419382_Russian.bin",
        "name_language": "Russian",
        "id_bin_language": "BossBabyCartoon_L5_1196419382_Russian"
      },
      {
        "author": "LMB Studio",
        "link_thumb": "https://live.staticflickr.com/65535/51781043245_ab2d61494a_o.gif",
        "link_bin": "https://github.com/lmbstudiocontact/mb5_1/raw/main/BossBabyCartoon_L5_1196419382_Spanish.bin",
        "name_language": "Spanish",
        "id_bin_language": "BossBabyCartoon_L5_1196419382_Spanish"
      }
    ],
    "array_tags": [
      "lmbstudio"
    ],
    "list_album": [
      {
        "id_album": "158762705",
        "link_thumb": "https://live.staticflickr.com/65535/51780801109_51d4991428_o.gif",
        "title": "Boss Baby Cartoon_L5"
      }
    ]
  },
  {
    "author": "NIXIAH",
    "link_thumb": "https://live.staticflickr.com/65535/51694421778_7bb4a114ee_o.gif",
    "link_bin": "https://github.com/lmbstudiocontact/mb5_0/raw/main/239.bin",
    "id_bin": "239",
    "list_language": [],
    "array_tags": [
      "digital",
      "date",
      "heartrate",
      "battery",
      "steps"
    ],
    "list_album": [
      {
        "id_album": "2433880",
        "link_thumb": "https://live.staticflickr.com/65535/51694421778_7bb4a114ee_o.gif",
        "title": "None"
      }
    ]
  },
  {
    "author": "Ben.Hoang",
    "link_thumb": "https://live.staticflickr.com/65535/51694060866_c534fe4f2f_o.gif",
    "link_bin": "https://github.com/lmbstudiocontact/mb5_0/raw/main/16.bin",
    "id_bin": "16",
    "list_language": [],
    "array_tags": [
      "steps"
    ],
    "list_album": [
      {
        "id_album": "63410260",
        "link_thumb": "https://live.staticflickr.com/65535/51694060866_c534fe4f2f_o.gif",
        "title": "Anime"
      }
    ]
  },
  {
    "author": "LMB Studio",
    "link_thumb": "https://live.staticflickr.com/65535/51695767409_6f64fdfc57_o.gif",
    "link_bin": "https://github.com/lmbstudiocontact/mb5_3/raw/main/Boy_L6_-305595962.bin",
    "id_bin": "Boy_L6_-305595962",
    "list_language": [
      {
        "author": "LMB Studio",
        "link_thumb": "https://live.staticflickr.com/65535/51694295652_c76a392256_o.gif",
        "link_bin": "https://github.com/lmbstudiocontact/mb5_3/raw/main/Boy_L6_-305595962_English.bin",
        "name_language": "English",
        "id_bin_language": "Boy_L6_-305595962_English"
      },
      {
        "author": "LMB Studio",
        "link_thumb": "https://live.staticflickr.com/65535/51695087371_c3734607d0_o.gif",
        "link_bin": "https://github.com/lmbstudiocontact/mb5_3/raw/main/Boy_L6_-305595962_Portuguese.bin",
        "name_language": "Portuguese",
        "id_bin_language": "Boy_L6_-305595962_Portuguese"
      },
      {
        "author": "LMB Studio",
        "link_thumb": "https://live.staticflickr.com/65535/51695363463_9152878be8_o.gif",
        "link_bin": "https://github.com/lmbstudiocontact/mb5_3/raw/main/Boy_L6_-305595962_Russian.bin",
        "name_language": "Russian",
        "id_bin_language": "Boy_L6_-305595962_Russian"
      },
      {
        "author": "LMB Studio",
        "link_thumb": "https://live.staticflickr.com/65535/51694296757_fe4f6460e8_o.gif",
        "link_bin": "https://github.com/lmbstudiocontact/mb5_3/raw/main/Boy_L6_-305595962_Spanish.bin",
        "name_language": "Spanish",
        "id_bin_language": "Boy_L6_-305595962_Spanish"
      }
    ],
    "array_tags": [
      "lmbstudio"
    ],
    "list_album": [
      {
        "id_album": "1995733213",
        "link_thumb": "https://live.staticflickr.com/65535/51695767409_6f64fdfc57_o.gif",
        "title": "Boy_L6"
      }
    ]
  },
  {
    "author": "Soul89reg",
    "link_thumb": "https://live.staticflickr.com/65535/51695014900_f2b9d909cd_o.gif",
    "link_bin": "https://github.com/lmbstudiocontact/mb5_12/raw/main/2124.bin",
    "id_bin": "2124",
    "list_language": [],
    "array_tags": [
      "digital",
      "date",
      "seconds",
      "distance",
      "heartrate",
      "calories",
      "battery",
      "steps"
    ],
    "list_album": [
      {
        "id_album": "2433880",
        "link_thumb": "https://live.staticflickr.com/65535/51695014900_f2b9d909cd_o.gif",
        "title": "None"
      }
    ]
  },
  {
    "author": "iamstven",
    "link_thumb": "https://live.staticflickr.com/65535/51694391256_5aed6fa8a5_o.gif",
    "link_bin": "https://github.com/lmbstudiocontact/mb5_3/raw/main/729.bin",
    "id_bin": "729",
    "list_language": [],
    "array_tags": [
      "weather",
      "calories",
      "steps"
    ],
    "list_album": [
      {
        "id_album": "2433880",
        "link_thumb": "https://live.staticflickr.com/65535/51694391256_5aed6fa8a5_o.gif",
        "title": "None"
      }
    ]
  },
  {
    "author": "brannik",
    "link_thumb": "https://live.staticflickr.com/65535/51694139306_9a3038469b_o.gif",
    "link_bin": "https://github.com/lmbstudiocontact/mb5_12/raw/main/2242.bin",
    "id_bin": "2242",
    "list_language": [],
    "array_tags": [
      "date",
      "distance",
      "heartrate",
      "weather",
      "pai",
      "time",
      "calories",
      "battery",
      "steps",
      "status"
    ],
    "list_album": [
      {
        "id_album": "2433880",
        "link_thumb": "https://live.staticflickr.com/65535/51694139306_9a3038469b_o.gif",
        "title": "None"
      }
    ]
  },
  {
    "author": "Ben.Hoang",
    "link_thumb": "https://live.staticflickr.com/65535/51694344993_2a74cd2732_o.gif",
    "link_bin": "https://github.com/lmbstudiocontact/mb5_0/raw/main/17.bin",
    "id_bin": "17",
    "list_language": [],
    "array_tags": [
      "steps"
    ],
    "list_album": [
      {
        "id_album": "63410260",
        "link_thumb": "https://live.staticflickr.com/65535/51694344993_2a74cd2732_o.gif",
        "title": "Anime"
      }
    ]
  },
  {
    "author": "None",
    "link_thumb": "https://live.staticflickr.com/65535/51694901189_a01ab8b583_o.gif",
    "link_bin": "https://github.com/lmbstudiocontact/mb5_0/raw/main/30_fix.bin",
    "id_bin": "30_fix",
    "list_language": [],
    "array_tags": [],
    "list_album": [
      {
        "id_album": "63410260",
        "link_thumb": "https://live.staticflickr.com/65535/51694901189_a01ab8b583_o.gif",
        "title": "Anime"
      }
    ]
  },
  {
    "author": "Mirbo",
    "link_thumb": "https://live.staticflickr.com/65535/51694444246_549f3d7e8e_o.gif",
    "link_bin": "https://github.com/lmbstudiocontact/mb5_23/raw/main/980.bin",
    "id_bin": "980",
    "list_language": [],
    "array_tags": [
      "date",
      "weekday",
      "time",
      "battery",
      "steps"
    ],
    "list_album": [
      {
        "id_album": "2433880",
        "link_thumb": "https://live.staticflickr.com/65535/51694444246_549f3d7e8e_o.gif",
        "title": "None"
      }
    ]
  },
  {
    "author": "LMB Studio",
    "link_thumb": "https://live.staticflickr.com/65535/51780801329_44dd88595f_o.gif",
    "link_bin": "https://github.com/lmbstudiocontact/mb5_1/raw/main/BossBabyCartoon_L5_446268251.bin",
    "id_bin": "BossBabyCartoon_L5_446268251",
    "list_language": [
      {
        "author": "LMB Studio",
        "link_thumb": "https://live.staticflickr.com/65535/51781043530_6720d4ce21_o.gif",
        "link_bin": "https://github.com/lmbstudiocontact/mb5_1/raw/main/BossBabyCartoon_L5_446268251_English.bin",
        "name_language": "English",
        "id_bin_language": "BossBabyCartoon_L5_446268251_English"
      },
      {
        "author": "LMB Studio",
        "link_thumb": "https://live.staticflickr.com/65535/51780160131_2487ce1b10_o.gif",
        "link_bin": "https://github.com/lmbstudiocontact/mb5_1/raw/main/BossBabyCartoon_L5_446268251_Portuguese.bin",
        "name_language": "Portuguese",
        "id_bin_language": "BossBabyCartoon_L5_446268251_Portuguese"
      },
      {
        "author": "LMB Studio",
        "link_thumb": "https://live.staticflickr.com/65535/51780160096_8505fee3b8_o.gif",
        "link_bin": "https://github.com/lmbstudiocontact/mb5_1/raw/main/BossBabyCartoon_L5_446268251_Russian.bin",
        "name_language": "Russian",
        "id_bin_language": "BossBabyCartoon_L5_446268251_Russian"
      },
      {
        "author": "LMB Studio",
        "link_thumb": "https://live.staticflickr.com/65535/51780160041_2e12e815d2_o.gif",
        "link_bin": "https://github.com/lmbstudiocontact/mb5_1/raw/main/BossBabyCartoon_L5_446268251_Spanish.bin",
        "name_language": "Spanish",
        "id_bin_language": "BossBabyCartoon_L5_446268251_Spanish"
      }
    ],
    "array_tags": [
      "lmbstudio"
    ],
    "list_album": [
      {
        "id_album": "158762705",
        "link_thumb": "https://live.staticflickr.com/65535/51780801329_44dd88595f_o.gif",
        "title": "Boss Baby Cartoon_L5"
      }
    ]
  },
  {
    "author": "ama3ing",
    "link_thumb": "https://live.staticflickr.com/65535/51695235275_d16c61684f_o.gif",
    "link_bin": "https://github.com/lmbstudiocontact/mb5_0/raw/main/519.bin",
    "id_bin": "519",
    "list_language": [],
    "array_tags": [
      "digital",
      "date",
      "distance",
      "heartrate",
      "weather",
      "calories",
      "battery",
      "steps"
    ],
    "list_album": [
      {
        "id_album": "2433880",
        "link_thumb": "https://live.staticflickr.com/65535/51695235275_d16c61684f_o.gif",
        "title": "None"
      }
    ]
  },
  {
    "author": "None",
    "link_thumb": "https://live.staticflickr.com/65535/51694592098_c918b7e2a3_o.gif",
    "link_bin": "https://github.com/lmbstudiocontact/mb5_0/raw/main/387.bin",
    "id_bin": "387",
    "list_language": [],
    "array_tags": [],
    "list_album": [
      {
        "id_album": "2433880",
        "link_thumb": "https://live.staticflickr.com/65535/51694592098_c918b7e2a3_o.gif",
        "title": "None"
      }
    ]
  },
  {
    "author": "None",
    "link_thumb": "https://live.staticflickr.com/65535/51700056226_61ee9c6bd6_o.gif",
    "link_bin": "https://github.com/lmbstudiocontact/mb5_38/raw/main/M0045.bin",
    "id_bin": "M0045",
    "list_language": [],
    "array_tags": [],
    "list_album": [
      {
        "id_album": "-583089738",
        "link_thumb": "https://live.staticflickr.com/65535/51700056226_61ee9c6bd6_o.gif",
        "title": "Mifit Store"
      }
    ]
  },
  {
    "author": "becamer",
    "link_thumb": "https://live.staticflickr.com/65535/51694429336_0ddeeb1380_o.gif",
    "link_bin": "https://github.com/lmbstudiocontact/mb5_3/raw/main/92.bin",
    "id_bin": "92",
    "list_language": [],
    "array_tags": [
      "game",
      "green",
      "gta"
    ],
    "list_album": [
      {
        "id_album": "2231123",
        "link_thumb": "https://live.staticflickr.com/65535/51694429336_0ddeeb1380_o.gif",
        "title": "Guns"
      }
    ]
  },
  {
    "author": "ahidzatx",
    "link_thumb": "https://live.staticflickr.com/65535/51693620862_0309b2e9de_o.gif",
    "link_bin": "https://github.com/lmbstudiocontact/mb5_3/raw/main/844.bin",
    "id_bin": "844",
    "list_language": [],
    "array_tags": [
      "digital",
      "date",
      "seconds",
      "distance",
      "heartrate",
      "weather",
      "calories",
      "battery",
      "steps"
    ],
    "list_album": [
      {
        "id_album": "2433880",
        "link_thumb": "https://live.staticflickr.com/65535/51693620862_0309b2e9de_o.gif",
        "title": "None"
      }
    ]
  },
  {
    "author": "None",
    "link_thumb": "https://live.staticflickr.com/65535/51700058361_379e56f5fb_o.gif",
    "link_bin": "https://github.com/lmbstudiocontact/mb5_38/raw/main/M0047.bin",
    "id_bin": "M0047",
    "list_language": [],
    "array_tags": [],
    "list_album": [
      {
        "id_album": "-583089738",
        "link_thumb": "https://live.staticflickr.com/65535/51700058361_379e56f5fb_o.gif",
        "title": "Mifit Store"
      }
    ]
  },
  {
    "author": "Ariq Noor Badruddoza",
    "link_thumb": "https://live.staticflickr.com/65535/51693206597_16a78130ee_o.gif",
    "link_bin": "https://github.com/lmbstudiocontact/mb5_12/raw/main/1233.bin",
    "id_bin": "1233",
    "list_language": [],
    "array_tags": [
      "digital",
      "date",
      "weather",
      "battery",
      "steps"
    ],
    "list_album": [
      {
        "id_album": "2433880",
        "link_thumb": "https://live.staticflickr.com/65535/51693206597_16a78130ee_o.gif",
        "title": "None"
      }
    ]
  },
  {
    "author": "sgssantos",
    "link_thumb": "https://live.staticflickr.com/65535/51694365208_dcd036d341_o.gif",
    "link_bin": "https://github.com/lmbstudiocontact/mb5_12/raw/main/1858.bin",
    "id_bin": "1858",
    "list_language": [],
    "array_tags": [
      "digital",
      "date",
      "distance",
      "heartrate",
      "weather",
      "alarm",
      "temperature",
      "battery",
      "steps"
    ],
    "list_album": [
      {
        "id_album": "2433880",
        "link_thumb": "https://live.staticflickr.com/65535/51694365208_dcd036d341_o.gif",
        "title": "None"
      }
    ]
  },
  {
    "author": "PaTRiKa871",
    "link_thumb": "https://live.staticflickr.com/65535/51693992996_0137243e95_o.gif",
    "link_bin": "https://github.com/lmbstudiocontact/mb5_12/raw/main/1173.bin",
    "id_bin": "1173",
    "list_language": [],
    "array_tags": [
      "digital",
      "date",
      "battery",
      "steps"
    ],
    "list_album": [
      {
        "id_album": "2433880",
        "link_thumb": "https://live.staticflickr.com/65535/51693992996_0137243e95_o.gif",
        "title": "None"
      }
    ]
  },
  {
    "author": "becamer",
    "link_thumb": "https://live.staticflickr.com/65535/51694700663_d53608909f_o.gif",
    "link_bin": "https://github.com/lmbstudiocontact/mb5_3/raw/main/91.bin",
    "id_bin": "91",
    "list_language": [],
    "array_tags": [
      "game",
      "blue",
      "gta"
    ],
    "list_album": [
      {
        "id_album": "2231123",
        "link_thumb": "https://live.staticflickr.com/65535/51694700663_d53608909f_o.gif",
        "title": "Guns"
      }
    ]
  },
  {
    "author": "awrun",
    "link_thumb": "https://live.staticflickr.com/65535/51694853699_476a61e444_o.gif",
    "link_bin": "https://github.com/lmbstudiocontact/mb5_0/raw/main/268.bin",
    "id_bin": "268",
    "list_language": [],
    "array_tags": [
      "digital",
      "date",
      "heartrate",
      "weather",
      "humidity",
      "battery",
      "steps",
      "wind"
    ],
    "list_album": [
      {
        "id_album": "2433880",
        "link_thumb": "https://live.staticflickr.com/65535/51694853699_476a61e444_o.gif",
        "title": "None"
      }
    ]
  },
  {
    "author": "sgssantos",
    "link_thumb": "https://live.staticflickr.com/65535/51693288687_d33f1f3ef0_o.gif",
    "link_bin": "https://github.com/lmbstudiocontact/mb5_12/raw/main/1773.bin",
    "id_bin": "1773",
    "list_language": [],
    "array_tags": [
      "digital",
      "date",
      "heartrate",
      "weather",
      "battery",
      "steps"
    ],
    "list_album": [
      {
        "id_album": "2433880",
        "link_thumb": "https://live.staticflickr.com/65535/51693288687_d33f1f3ef0_o.gif",
        "title": "None"
      }
    ]
  },
  {
    "author": "RuleDJ",
    "link_thumb": "https://live.staticflickr.com/65535/51694398498_a21001125a_o.gif",
    "link_bin": "https://github.com/lmbstudiocontact/mb5_12/raw/main/2121.bin",
    "id_bin": "2121",
    "list_language": [],
    "array_tags": [
      "digital",
      "date",
      "heartrate",
      "weather",
      "alarm",
      "humidity",
      "dnd",
      "battery"
    ],
    "list_album": [
      {
        "id_album": "2433880",
        "link_thumb": "https://live.staticflickr.com/65535/51694398498_a21001125a_o.gif",
        "title": "None"
      }
    ]
  },
  {
    "author": "None",
    "link_thumb": "https://live.staticflickr.com/65535/51695022829_f105830d5b_o.gif",
    "link_bin": "https://github.com/lmbstudiocontact/mb5_0/raw/main/511.bin",
    "id_bin": "511",
    "list_language": [],
    "array_tags": [],
    "list_album": [
      {
        "id_album": "2433880",
        "link_thumb": "https://live.staticflickr.com/65535/51695022829_f105830d5b_o.gif",
        "title": "None"
      }
    ]
  },
  {
    "author": "Eliud",
    "link_thumb": "https://live.staticflickr.com/65535/51694770204_ceef2e9275_o.gif",
    "link_bin": "https://github.com/lmbstudiocontact/mb5_12/raw/main/1867.bin",
    "id_bin": "1867",
    "list_language": [],
    "array_tags": [
      "watchface",
      "miband5"
    ],
    "list_album": [
      {
        "id_album": "2433880",
        "link_thumb": "https://live.staticflickr.com/65535/51694770204_ceef2e9275_o.gif",
        "title": "None"
      }
    ]
  },
  {
    "author": "shymik",
    "link_thumb": "https://live.staticflickr.com/65535/51694649444_a942c93470_o.gif",
    "link_bin": "https://github.com/lmbstudiocontact/mb5_12/raw/main/1030.bin",
    "id_bin": "1030",
    "list_language": [],
    "array_tags": [
      "digital",
      "date",
      "distance",
      "heartrate",
      "weather",
      "calories",
      "battery",
      "steps"
    ],
    "list_album": [
      {
        "id_album": "2433880",
        "link_thumb": "https://live.staticflickr.com/65535/51694649444_a942c93470_o.gif",
        "title": "None"
      }
    ]
  },
  {
    "author": "None",
    "link_thumb": "https://live.staticflickr.com/65535/51695127485_5aa843f173_o.gif",
    "link_bin": "https://github.com/lmbstudiocontact/mb5_0/raw/main/31_fix.bin",
    "id_bin": "31_fix",
    "list_language": [],
    "array_tags": [],
    "list_album": [
      {
        "id_album": "63410260",
        "link_thumb": "https://live.staticflickr.com/65535/51695127485_5aa843f173_o.gif",
        "title": "Anime"
      }
    ]
  },
  {
    "author": "Crypto1",
    "link_thumb": "https://live.staticflickr.com/65535/51694990535_1acfdeb8af_o.gif",
    "link_bin": "https://github.com/lmbstudiocontact/mb5_12/raw/main/1925.bin",
    "id_bin": "1925",
    "list_language": [],
    "array_tags": [
      "gif",
      "animation"
    ],
    "list_album": [
      {
        "id_album": "2433880",
        "link_thumb": "https://live.staticflickr.com/65535/51694990535_1acfdeb8af_o.gif",
        "title": "None"
      }
    ]
  },
  {
    "author": "None",
    "link_thumb": "https://live.staticflickr.com/65535/51700737144_c95c59cab2_o.gif",
    "link_bin": "https://github.com/lmbstudiocontact/mb5_38/raw/main/M0050.bin",
    "id_bin": "M0050",
    "list_language": [
      {
        "author": "None",
        "link_thumb": "https://live.staticflickr.com/65535/51701924048_7d45f2ff87_o.gif",
        "link_bin": "https://github.com/lmbstudiocontact/mb5_38/raw/main/M0050_English.bin",
        "name_language": "English",
        "id_bin_language": "M0050_English"
      },
      {
        "author": "None",
        "link_thumb": "https://live.staticflickr.com/65535/51699265542_ce2e9dd23c_o.gif",
        "link_bin": "https://github.com/lmbstudiocontact/mb5_38/raw/main/M0050_Portuguese.bin",
        "name_language": "Portuguese",
        "id_bin_language": "M0050_Portuguese"
      },
      {
        "author": "None",
        "link_thumb": "https://live.staticflickr.com/65535/51700950035_3c8d2c5483_o.gif",
        "link_bin": "https://github.com/lmbstudiocontact/mb5_38/raw/main/M0050_Russian.bin",
        "name_language": "Russian",
        "id_bin_language": "M0050_Russian"
      },
      {
        "author": "None",
        "link_thumb": "https://live.staticflickr.com/65535/51700950385_930de5dcbf_o.gif",
        "link_bin": "https://github.com/lmbstudiocontact/mb5_38/raw/main/M0050_Spanish.bin",
        "name_language": "Spanish",
        "id_bin_language": "M0050_Spanish"
      }
    ],
    "array_tags": [],
    "list_album": [
      {
        "id_album": "-583089738",
        "link_thumb": "https://live.staticflickr.com/65535/51700737144_c95c59cab2_o.gif",
        "title": "Mifit Store"
      }
    ]
  },
  {
    "author": "Medozavr",
    "link_thumb": "https://live.staticflickr.com/65535/51694891610_9a87fe61da_o.gif",
    "link_bin": "https://github.com/lmbstudiocontact/mb5_12/raw/main/1255.bin",
    "id_bin": "1255",
    "list_language": [],
    "array_tags": [
      "animation"
    ],
    "list_album": [
      {
        "id_album": "2433880",
        "link_thumb": "https://live.staticflickr.com/65535/51694891610_9a87fe61da_o.gif",
        "title": "None"
      }
    ]
  },
  {
    "author": "becamer",
    "link_thumb": "https://live.staticflickr.com/65535/51695102569_15b6cacab4_o.gif",
    "link_bin": "https://github.com/lmbstudiocontact/mb5_3/raw/main/90.bin",
    "id_bin": "90",
    "list_language": [],
    "array_tags": [
      "game",
      "gta"
    ],
    "list_album": [
      {
        "id_album": "2231123",
        "link_thumb": "https://live.staticflickr.com/65535/51695102569_15b6cacab4_o.gif",
        "title": "Guns"
      }
    ]
  },
  {
    "author": "None",
    "link_thumb": "https://live.staticflickr.com/65535/51700336683_9e277df715_o.gif",
    "link_bin": "https://github.com/lmbstudiocontact/mb5_38/raw/main/M0048.bin",
    "id_bin": "M0048",
    "list_language": [
      {
        "author": "None",
        "link_thumb": "https://live.staticflickr.com/65535/51700337278_2808f1965e_o.gif",
        "link_bin": "https://github.com/lmbstudiocontact/mb5_38/raw/main/M0048_English.bin",
        "name_language": "English",
        "id_bin_language": "M0048_English"
      },
      {
        "author": "None",
        "link_thumb": "https://live.staticflickr.com/65535/51700059501_3f8b65390d_o.gif",
        "link_bin": "https://github.com/lmbstudiocontact/mb5_38/raw/main/M0048_Portuguese.bin",
        "name_language": "Portuguese",
        "id_bin_language": "M0048_Portuguese"
      },
      {
        "author": "None",
        "link_thumb": "https://live.staticflickr.com/65535/51700059781_5a28587da6_o.gif",
        "link_bin": "https://github.com/lmbstudiocontact/mb5_38/raw/main/M0048_Russian.bin",
        "name_language": "Russian",
        "id_bin_language": "M0048_Russian"
      },
      {
        "author": "None",
        "link_thumb": "https://live.staticflickr.com/65535/51700060351_7f9bd5922e_o.gif",
        "link_bin": "https://github.com/lmbstudiocontact/mb5_38/raw/main/M0048_Spanish.bin",
        "name_language": "Spanish",
        "id_bin_language": "M0048_Spanish"
      }
    ],
    "array_tags": [],
    "list_album": [
      {
        "id_album": "-583089738",
        "link_thumb": "https://live.staticflickr.com/65535/51700336683_9e277df715_o.gif",
        "title": "Mifit Store"
      }
    ]
  },
  {
    "author": "nekofirefox_AR",
    "link_thumb": "https://live.staticflickr.com/65535/51694247748_7ff4b9e05e_o.gif",
    "link_bin": "https://github.com/lmbstudiocontact/mb5_12/raw/main/1038.bin",
    "id_bin": "1038",
    "list_language": [],
    "array_tags": [
      "digital",
      "heartrate"
    ],
    "list_album": [
      {
        "id_album": "2433880",
        "link_thumb": "https://live.staticflickr.com/65535/51694247748_7ff4b9e05e_o.gif",
        "title": "None"
      }
    ]
  },
  {
    "author": "None",
    "link_thumb": "https://live.staticflickr.com/65535/51700060706_fa197c057c_o.gif",
    "link_bin": "https://github.com/lmbstudiocontact/mb5_38/raw/main/M0049.bin",
    "id_bin": "M0049",
    "list_language": [
      {
        "author": "None",
        "link_thumb": "https://live.staticflickr.com/65535/51700735514_e48a386813_o.gif",
        "link_bin": "https://github.com/lmbstudiocontact/mb5_38/raw/main/M0049_English.bin",
        "name_language": "English",
        "id_bin_language": "M0049_English"
      },
      {
        "author": "None",
        "link_thumb": "https://live.staticflickr.com/65535/51700061411_809b2f9567_o.gif",
        "link_bin": "https://github.com/lmbstudiocontact/mb5_38/raw/main/M0049_Portuguese.bin",
        "name_language": "Portuguese",
        "id_bin_language": "M0049_Portuguese"
      },
      {
        "author": "None",
        "link_thumb": "https://live.staticflickr.com/65535/51700061786_b1f00d651b_o.gif",
        "link_bin": "https://github.com/lmbstudiocontact/mb5_38/raw/main/M0049_Russian.bin",
        "name_language": "Russian",
        "id_bin_language": "M0049_Russian"
      },
      {
        "author": "None",
        "link_thumb": "https://live.staticflickr.com/65535/51700736774_a9a6a7dc58_o.gif",
        "link_bin": "https://github.com/lmbstudiocontact/mb5_38/raw/main/M0049_Spanish.bin",
        "name_language": "Spanish",
        "id_bin_language": "M0049_Spanish"
      }
    ],
    "array_tags": [],
    "list_album": [
      {
        "id_album": "-583089738",
        "link_thumb": "https://live.staticflickr.com/65535/51700060706_fa197c057c_o.gif",
        "title": "Mifit Store"
      }
    ]
  },
  {
    "author": "awrun",
    "link_thumb": "https://live.staticflickr.com/65535/51694135906_815caeb17c_o.gif",
    "link_bin": "https://github.com/lmbstudiocontact/mb5_0/raw/main/221.bin",
    "id_bin": "221",
    "list_language": [],
    "array_tags": [
      "digital",
      "date",
      "distance",
      "heartrate",
      "weather",
      "calories",
      "battery",
      "steps"
    ],
    "list_album": [
      {
        "id_album": "2433880",
        "link_thumb": "https://live.staticflickr.com/65535/51694135906_815caeb17c_o.gif",
        "title": "None"
      }
    ]
  },
  {
    "author": "LMB Studio",
    "link_thumb": "https://live.staticflickr.com/65535/51694313552_a128bdab01_o.gif",
    "link_bin": "https://github.com/lmbstudiocontact/mb5_3/raw/main/Boy_L6_-988175456.bin",
    "id_bin": "Boy_L6_-988175456",
    "list_language": [
      {
        "author": "LMB Studio",
        "link_thumb": "https://live.staticflickr.com/65535/51695786344_7bf7710714_o.gif",
        "link_bin": "https://github.com/lmbstudiocontact/mb5_3/raw/main/Boy_L6_-988175456_English.bin",
        "name_language": "English",
        "id_bin_language": "Boy_L6_-988175456_English"
      },
      {
        "author": "LMB Studio",
        "link_thumb": "https://live.staticflickr.com/65535/51695382433_817bec96b2_o.gif",
        "link_bin": "https://github.com/lmbstudiocontact/mb5_3/raw/main/Boy_L6_-988175456_Portuguese.bin",
        "name_language": "Portuguese",
        "id_bin_language": "Boy_L6_-988175456_Portuguese"
      },
      {
        "author": "LMB Studio",
        "link_thumb": "https://live.staticflickr.com/65535/51695998395_3ab60d4295_o.gif",
        "link_bin": "https://github.com/lmbstudiocontact/mb5_3/raw/main/Boy_L6_-988175456_Russian.bin",
        "name_language": "Russian",
        "id_bin_language": "Boy_L6_-988175456_Russian"
      },
      {
        "author": "LMB Studio",
        "link_thumb": "https://live.staticflickr.com/65535/51694315247_3479d5bf78_o.gif",
        "link_bin": "https://github.com/lmbstudiocontact/mb5_3/raw/main/Boy_L6_-988175456_Spanish.bin",
        "name_language": "Spanish",
        "id_bin_language": "Boy_L6_-988175456_Spanish"
      }
    ],
    "array_tags": [
      "lmbstudio"
    ],
    "list_album": [
      {
        "id_album": "1995733213",
        "link_thumb": "https://live.staticflickr.com/65535/51694313552_a128bdab01_o.gif",
        "title": "Boy_L6"
      }
    ]
  },
  {
    "author": "gouzi01",
    "link_thumb": "https://live.staticflickr.com/65535/51694701794_187e388cdb_o.gif",
    "link_bin": "https://github.com/lmbstudiocontact/mb5_12/raw/main/1397.bin",
    "id_bin": "1397",
    "list_language": [],
    "array_tags": [
      "digital",
      "date",
      "analog",
      "distance",
      "heartrate",
      "weather",
      "calories",
      "battery",
      "steps"
    ],
    "list_album": [
      {
        "id_album": "2433880",
        "link_thumb": "https://live.staticflickr.com/65535/51694701794_187e388cdb_o.gif",
        "title": "None"
      }
    ]
  },
  {
    "author": "themoneyfactory",
    "link_thumb": "https://live.staticflickr.com/65535/51694360366_7cc21fd309_o.gif",
    "link_bin": "https://github.com/lmbstudiocontact/mb5_3/raw/main/585.bin",
    "id_bin": "585",
    "list_language": [],
    "array_tags": [
      "digital",
      "date",
      "seconds",
      "battery"
    ],
    "list_album": [
      {
        "id_album": "2433880",
        "link_thumb": "https://live.staticflickr.com/65535/51694360366_7cc21fd309_o.gif",
        "title": "None"
      }
    ]
  },
  {
    "author": "LMB Studio",
    "link_thumb": "https://live.staticflickr.com/65535/51694301142_460afc8c69_o.gif",
    "link_bin": "https://github.com/lmbstudiocontact/mb5_3/raw/main/Boy_L6_-418159930.bin",
    "id_bin": "Boy_L6_-418159930",
    "list_language": [
      {
        "author": "LMB Studio",
        "link_thumb": "https://live.staticflickr.com/65535/51695368843_59587da2a8_o.gif",
        "link_bin": "https://github.com/lmbstudiocontact/mb5_3/raw/main/Boy_L6_-418159930_English.bin",
        "name_language": "English",
        "id_bin_language": "Boy_L6_-418159930_English"
      },
      {
        "author": "LMB Studio",
        "link_thumb": "https://live.staticflickr.com/65535/51695774009_e82ca15419_o.gif",
        "link_bin": "https://github.com/lmbstudiocontact/mb5_3/raw/main/Boy_L6_-418159930_Portuguese.bin",
        "name_language": "Portuguese",
        "id_bin_language": "Boy_L6_-418159930_Portuguese"
      },
      {
        "author": "LMB Studio",
        "link_thumb": "https://live.staticflickr.com/65535/51695369953_5d9701f66a_o.gif",
        "link_bin": "https://github.com/lmbstudiocontact/mb5_3/raw/main/Boy_L6_-418159930_Russian.bin",
        "name_language": "Russian",
        "id_bin_language": "Boy_L6_-418159930_Russian"
      },
      {
        "author": "LMB Studio",
        "link_thumb": "https://live.staticflickr.com/65535/51694302972_aa195923cd_o.gif",
        "link_bin": "https://github.com/lmbstudiocontact/mb5_3/raw/main/Boy_L6_-418159930_Spanish.bin",
        "name_language": "Spanish",
        "id_bin_language": "Boy_L6_-418159930_Spanish"
      }
    ],
    "array_tags": [
      "lmbstudio"
    ],
    "list_album": [
      {
        "id_album": "1995733213",
        "link_thumb": "https://live.staticflickr.com/65535/51694301142_460afc8c69_o.gif",
        "title": "Boy_L6"
      }
    ]
  },
  {
    "author": "Orange12",
    "link_thumb": "https://live.staticflickr.com/65535/51693343227_0117e547f8_o.gif",
    "link_bin": "https://github.com/lmbstudiocontact/mb5_0/raw/main/222.bin",
    "id_bin": "222",
    "list_language": [],
    "array_tags": [
      "weather"
    ],
    "list_album": [
      {
        "id_album": "2433880",
        "link_thumb": "https://live.staticflickr.com/65535/51693343227_0117e547f8_o.gif",
        "title": "None"
      }
    ]
  },
  {
    "author": "LMB Studio",
    "link_thumb": "https://live.staticflickr.com/65535/51694299102_5ce5231e54_o.gif",
    "link_bin": "https://github.com/lmbstudiocontact/mb5_3/raw/main/Boy_L6_-418159926.bin",
    "id_bin": "Boy_L6_-418159926",
    "list_language": [
      {
        "author": "LMB Studio",
        "link_thumb": "https://live.staticflickr.com/65535/51695366503_c9718363a1_o.gif",
        "link_bin": "https://github.com/lmbstudiocontact/mb5_3/raw/main/Boy_L6_-418159926_English.bin",
        "name_language": "English",
        "id_bin_language": "Boy_L6_-418159926_English"
      },
      {
        "author": "LMB Studio",
        "link_thumb": "https://live.staticflickr.com/65535/51694299942_0d012a75e5_o.gif",
        "link_bin": "https://github.com/lmbstudiocontact/mb5_3/raw/main/Boy_L6_-418159926_Portuguese.bin",
        "name_language": "Portuguese",
        "id_bin_language": "Boy_L6_-418159926_Portuguese"
      },
      {
        "author": "LMB Studio",
        "link_thumb": "https://live.staticflickr.com/65535/51695367548_2421f088c9_o.gif",
        "link_bin": "https://github.com/lmbstudiocontact/mb5_3/raw/main/Boy_L6_-418159926_Russian.bin",
        "name_language": "Russian",
        "id_bin_language": "Boy_L6_-418159926_Russian"
      },
      {
        "author": "LMB Studio",
        "link_thumb": "https://live.staticflickr.com/65535/51695772749_bd66301159_o.gif",
        "link_bin": "https://github.com/lmbstudiocontact/mb5_3/raw/main/Boy_L6_-418159926_Spanish.bin",
        "name_language": "Spanish",
        "id_bin_language": "Boy_L6_-418159926_Spanish"
      }
    ],
    "array_tags": [
      "lmbstudio"
    ],
    "list_album": [
      {
        "id_album": "1995733213",
        "link_thumb": "https://live.staticflickr.com/65535/51694299102_5ce5231e54_o.gif",
        "title": "Boy_L6"
      }
    ]
  },
  {
    "author": "ilidio.martins",
    "link_thumb": "https://live.staticflickr.com/65535/51693304582_18fc0cfedb_o.gif",
    "link_bin": "https://github.com/lmbstudiocontact/mb5_12/raw/main/1893.bin",
    "id_bin": "1893",
    "list_language": [],
    "array_tags": [
      "digital",
      "distance",
      "heartrate",
      "weather",
      "battery",
      "steps"
    ],
    "list_album": [
      {
        "id_album": "2433880",
        "link_thumb": "https://live.staticflickr.com/65535/51693304582_18fc0cfedb_o.gif",
        "title": "None"
      }
    ]
  },
  {
    "author": "RikardoTranzilo",
    "link_thumb": "https://live.staticflickr.com/65535/51693371262_ae72af86d3_o.gif",
    "link_bin": "https://github.com/lmbstudiocontact/mb5_22/raw/main/2568.bin",
    "id_bin": "2568",
    "list_language": [],
    "array_tags": [
      "naruto",
      "digital",
      "brasil",
      "portugues"
    ],
    "list_album": [
      {
        "id_album": "63410260",
        "link_thumb": "https://live.staticflickr.com/65535/51693371262_ae72af86d3_o.gif",
        "title": "Anime"
      }
    ]
  },
  {
    "author": "LMB Studio",
    "link_thumb": "https://live.staticflickr.com/65535/51695151031_a4b8b725e8_o.gif",
    "link_bin": "https://github.com/lmbstudiocontact/mb5_3/raw/main/Boy_L6_537247521.bin",
    "id_bin": "Boy_L6_537247521",
    "list_language": [
      {
        "author": "LMB Studio",
        "link_thumb": "https://live.staticflickr.com/65535/51695832649_42d4f46754_o.gif",
        "link_bin": "https://github.com/lmbstudiocontact/mb5_3/raw/main/Boy_L6_537247521_English.bin",
        "name_language": "English",
        "id_bin_language": "Boy_L6_537247521_English"
      },
      {
        "author": "LMB Studio",
        "link_thumb": "https://live.staticflickr.com/65535/51694359827_8253991b7c_o.gif",
        "link_bin": "https://github.com/lmbstudiocontact/mb5_3/raw/main/Boy_L6_537247521_Portuguese.bin",
        "name_language": "Portuguese",
        "id_bin_language": "Boy_L6_537247521_Portuguese"
      },
      {
        "author": "LMB Studio",
        "link_thumb": "https://live.staticflickr.com/65535/51695833379_9e2c66274b_o.gif",
        "link_bin": "https://github.com/lmbstudiocontact/mb5_3/raw/main/Boy_L6_537247521_Russian.bin",
        "name_language": "Russian",
        "id_bin_language": "Boy_L6_537247521_Russian"
      },
      {
        "author": "LMB Studio",
        "link_thumb": "https://live.staticflickr.com/65535/51696044340_f33924411e_o.gif",
        "link_bin": "https://github.com/lmbstudiocontact/mb5_3/raw/main/Boy_L6_537247521_Spanish.bin",
        "name_language": "Spanish",
        "id_bin_language": "Boy_L6_537247521_Spanish"
      }
    ],
    "array_tags": [
      "lmbstudio"
    ],
    "list_album": [
      {
        "id_album": "1995733213",
        "link_thumb": "https://live.staticflickr.com/65535/51695151031_a4b8b725e8_o.gif",
        "title": "Boy_L6"
      }
    ]
  },
  {
    "author": "Dailson f.c",
    "link_thumb": "https://live.staticflickr.com/65535/51694681284_eb790b22e3_o.gif",
    "link_bin": "https://github.com/lmbstudiocontact/mb5_12/raw/main/1269.bin",
    "id_bin": "1269",
    "list_language": [],
    "array_tags": [
      "digital",
      "date",
      "distance",
      "heartrate",
      "weather",
      "calories",
      "battery",
      "steps"
    ],
    "list_album": [
      {
        "id_album": "2433880",
        "link_thumb": "https://live.staticflickr.com/65535/51694681284_eb790b22e3_o.gif",
        "title": "None"
      }
    ]
  },
  {
    "author": "cedL02",
    "link_thumb": "https://live.staticflickr.com/65535/51694146666_3ec6856543_o.gif",
    "link_bin": "https://github.com/lmbstudiocontact/mb5_12/raw/main/2344.bin",
    "id_bin": "2344",
    "list_language": [],
    "array_tags": [
      "date",
      "distance",
      "animated",
      "manga",
      "steps",
      "day",
      "anime"
    ],
    "list_album": [
      {
        "id_album": "63410260",
        "link_thumb": "https://live.staticflickr.com/65535/51694146666_3ec6856543_o.gif",
        "title": "Anime"
      }
    ]
  },
  {
    "author": "LMB Studio",
    "link_thumb": "https://live.staticflickr.com/65535/51695148931_49e42f49e4_o.gif",
    "link_bin": "https://github.com/lmbstudiocontact/mb5_3/raw/main/Boy_L6_537247328.bin",
    "id_bin": "Boy_L6_537247328",
    "list_language": [
      {
        "author": "LMB Studio",
        "link_thumb": "https://live.staticflickr.com/65535/51695426133_7282f4ab79_o.gif",
        "link_bin": "https://github.com/lmbstudiocontact/mb5_3/raw/main/Boy_L6_537247328_English.bin",
        "name_language": "English",
        "id_bin_language": "Boy_L6_537247328_English"
      },
      {
        "author": "LMB Studio",
        "link_thumb": "https://live.staticflickr.com/65535/51694357447_383691b1a5_o.gif",
        "link_bin": "https://github.com/lmbstudiocontact/mb5_3/raw/main/Boy_L6_537247328_Portuguese.bin",
        "name_language": "Portuguese",
        "id_bin_language": "Boy_L6_537247328_Portuguese"
      },
      {
        "author": "LMB Studio",
        "link_thumb": "https://live.staticflickr.com/65535/51694357932_cacf4b5a01_o.gif",
        "link_bin": "https://github.com/lmbstudiocontact/mb5_3/raw/main/Boy_L6_537247328_Russian.bin",
        "name_language": "Russian",
        "id_bin_language": "Boy_L6_537247328_Russian"
      },
      {
        "author": "LMB Studio",
        "link_thumb": "https://live.staticflickr.com/65535/51694358387_754f0f6fa6_o.gif",
        "link_bin": "https://github.com/lmbstudiocontact/mb5_3/raw/main/Boy_L6_537247328_Spanish.bin",
        "name_language": "Spanish",
        "id_bin_language": "Boy_L6_537247328_Spanish"
      }
    ],
    "array_tags": [
      "lmbstudio"
    ],
    "list_album": [
      {
        "id_album": "1995733213",
        "link_thumb": "https://live.staticflickr.com/65535/51695148931_49e42f49e4_o.gif",
        "title": "Boy_L6"
      }
    ]
  },
  {
    "author": "useooo01",
    "link_thumb": "https://live.staticflickr.com/65535/51694668429_0317cd8714_o.gif",
    "link_bin": "https://github.com/lmbstudiocontact/mb5_12/raw/main/1171.bin",
    "id_bin": "1171",
    "list_language": [],
    "array_tags": [
      "date",
      "digital",
      "battery"
    ],
    "list_album": [
      {
        "id_album": "2433880",
        "link_thumb": "https://live.staticflickr.com/65535/51694668429_0317cd8714_o.gif",
        "title": "None"
      }
    ]
  }
]